{"symbol":"ABR","updated":"2026-07-14T16:53:36.687860-04:00","underlyingPrice":5.0,"greeks":{"enabled":true,"primarySource":"cboe","fallbackSource":"client-black-scholes","riskFreeRate":null,"dividendYield":null,"total":241,"cboeMatched":241,"computed":0,"missing":0,"cboeContracts":326},"expirations":["2026-07-17","2026-07-24","2026-07-31","2026-08-07","2026-08-14","2026-08-21","2026-08-28","2026-10-16","2027-01-15","2028-01-21"],"quotes":[{"symbol":"ABR260717C00001000","expiration":"2026-07-17","side":"call","strike":1.0,"bid":3.7,"ask":4.1,"mid":3.9,"last":3.9,"volume":6.0,"openInterest":10.0,"iv":11.5000028125,"delta":0.99,"gamma":0.0066,"theta":-0.0109,"vega":0.0001,"rho":0.0001,"greeksSource":"cboe","greeksMissingReason":null},{"symbol":"ABR260717C00002000","expiration":"2026-07-17","side":"call","strike":2.0,"bid":2.8,"ask":3.1,"mid":2.95,"last":2.78,"volume":1.0,"openInterest":18.0,"iv":6.781251523437501,"delta":0.9808,"gamma":0.0195,"theta":-0.0114,"vega":0.0002,"rho":0.0003,"greeksSource":"cboe","greeksMissingReason":null},{"symbol":"ABR260717C00002500","expiration":"2026-07-17","side":"call","strike":2.5,"bid":2.35,"ask":2.65,"mid":2.5,"last":2.3,"volume":3.0,"openInterest":2.0,"iv":0.500005,"delta":0.9742,"gamma":0.032,"theta":-0.0116,"vega":0.0003,"rho":0.0004,"greeksSource":"cboe","greeksMissingReason":null},{"symbol":"ABR260717C00003000","expiration":"2026-07-17","side":"call","strike":3.0,"bid":1.9,"ask":2.1,"mid":2.0,"last":2.0,"volume":4.0,"openInterest":14.0,"iv":0.500005,"delta":0.9647,"gamma":0.0537,"theta":-0.012,"vega":0.0004,"rho":0.0005,"greeksSource":"cboe","greeksMissingReason":null},{"symbol":"ABR260717C00004000","expiration":"2026-07-17","side":"call","strike":4.0,"bid":0.95,"ask":1.1,"mid":1.025,"last":1.07,"volume":3.0,"openInterest":17.0,"iv":1.5000025,"delta":0.9176,"gamma":0.1986,"theta":-0.0134,"vega":0.0008,"rho":0.0006,"greeksSource":"cboe","greeksMissingReason":null},{"symbol":"ABR260717C00004500","expiration":"2026-07-17","side":"call","strike":4.5,"bid":0.1,"ask":0.8,"mid":0.45,"last":0.57,"volume":1.0,"openInterest":1.0,"iv":2.593753515625,"delta":0.8317,"gamma":0.5379,"theta":-0.0145,"vega":0.0013,"rho":0.0006,"greeksSource":"cboe","greeksMissingReason":null},{"symbol":"ABR260717C00005000","expiration":"2026-07-17","side":"call","strike":5.0,"bid":0.05,"ask":0.2,"mid":0.125,"last":0.11,"volume":71.0,"openInterest":563.0,"iv":0.6015664843750002,"delta":0.3898,"gamma":1.3342,"theta":-0.0145,"vega":0.002,"rho":0.0003,"greeksSource":"cboe","greeksMissingReason":null},{"symbol":"ABR260717C00005500","expiration":"2026-07-17","side":"call","strike":5.5,"bid":0.0,"ask":0.05,"mid":null,"last":0.03,"volume":3.0,"openInterest":366.0,"iv":0.7812521875,"delta":0.13,"gamma":0.4467,"theta":-0.0118,"vega":0.0011,"rho":0.0001,"greeksSource":"cboe","greeksMissingReason":null},{"symbol":"ABR260717C00006000","expiration":"2026-07-17","side":"call","strike":6.0,"bid":0.0,"ask":0.05,"mid":null,"last":0.01,"volume":1.0,"openInterest":250.0,"iv":1.2343788281249999,"delta":0.0706,"gamma":0.2109,"theta":-0.0094,"vega":0.0007,"rho":0.0,"greeksSource":"cboe","greeksMissingReason":null},{"symbol":"ABR260717C00007000","expiration":"2026-07-17","side":"call","strike":7.0,"bid":0.0,"ask":0.05,"mid":null,"last":0.03,"volume":9.0,"openInterest":178.0,"iv":1.9375003125,"delta":0.0318,"gamma":0.0796,"theta":-0.0062,"vega":0.0004,"rho":0.0,"greeksSource":"cboe","greeksMissingReason":null},{"symbol":"ABR260717C00008000","expiration":"2026-07-17","side":"call","strike":8.0,"bid":0.0,"ask":0.05,"mid":null,"last":0.02,"volume":10.0,"openInterest":1060.0,"iv":2.5312536718749996,"delta":0.018,"gamma":0.0405,"theta":-0.0043,"vega":0.0002,"rho":0.0,"greeksSource":"cboe","greeksMissingReason":null},{"symbol":"ABR260717C00009000","expiration":"2026-07-17","side":"call","strike":9.0,"bid":0.0,"ask":0.05,"mid":null,"last":0.02,"volume":1.0,"openInterest":1519.0,"iv":3.0000025,"delta":0.0113,"gamma":0.0239,"theta":-0.0031,"vega":0.0001,"rho":0.0,"greeksSource":"cboe","greeksMissingReason":null},{"symbol":"ABR260717C00010000","expiration":"2026-07-17","side":"call","strike":10.0,"bid":0.0,"ask":0.05,"mid":null,"last":0.05,"volume":2.0,"openInterest":623.0,"iv":3.43750140625,"delta":0.0076,"gamma":0.0153,"theta":-0.0023,"vega":0.0001,"rho":0.0,"greeksSource":"cboe","greeksMissingReason":null},{"symbol":"ABR260717C00011000","expiration":"2026-07-17","side":"call","strike":11.0,"bid":0.0,"ask":0.25,"mid":null,"last":0.09,"volume":6.0,"openInterest":63.0,"iv":5.1562535546875,"delta":0.0054,"gamma":0.0104,"theta":-0.0017,"vega":0.0001,"rho":0.0,"greeksSource":"cboe","greeksMissingReason":null},{"symbol":"ABR260717C00012000","expiration":"2026-07-17","side":"call","strike":12.0,"bid":0.0,"ask":0.15,"mid":null,"last":0.05,"volume":2.0,"openInterest":53.0,"iv":4.968753789062499,"delta":0.0039,"gamma":0.0074,"theta":-0.0013,"vega":0.0001,"rho":0.0,"greeksSource":"cboe","greeksMissingReason":null},{"symbol":"ABR260717C00013000","expiration":"2026-07-17","side":"call","strike":13.0,"bid":0.0,"ask":0.0,"mid":null,"last":0.03,"volume":1.0,"openInterest":0.0,"iv":0.500005,"delta":0.0029,"gamma":0.0054,"theta":-0.001,"vega":0.0,"rho":0.0,"greeksSource":"cboe","greeksMissingReason":null},{"symbol":"ABR260717C00014000","expiration":"2026-07-17","side":"call","strike":14.0,"bid":0.0,"ask":0.05,"mid":null,"last":0.05,"volume":1.0,"openInterest":4.0,"iv":4.6562541796875,"delta":0.0022,"gamma":0.004,"theta":-0.0008,"vega":0.0,"rho":0.0,"greeksSource":"cboe","greeksMissingReason":null},{"symbol":"ABR260717C00016000","expiration":"2026-07-17","side":"call","strike":16.0,"bid":0.0,"ask":0.0,"mid":null,"last":0.1,"volume":2.0,"openInterest":0.0,"iv":0.500005,"delta":0.0014,"gamma":0.0024,"theta":-0.0005,"vega":0.0,"rho":0.0,"greeksSource":"cboe","greeksMissingReason":null},{"symbol":"ABR260717P00001000","expiration":"2026-07-17","side":"put","strike":1.0,"bid":0.0,"ask":0.05,"mid":null,"last":0.02,"volume":1.0,"openInterest":1.0,"iv":8.500004687499999,"delta":-0.0102,"gamma":0.0066,"theta":-0.0114,"vega":0.0001,"rho":0.0,"greeksSource":"cboe","greeksMissingReason":null},{"symbol":"ABR260717P00002000","expiration":"2026-07-17","side":"put","strike":2.0,"bid":0.0,"ask":0.05,"mid":null,"last":0.02,"volume":3.0,"openInterest":16.0,"iv":4.937503828124999,"delta":-0.0195,"gamma":0.0195,"theta":-0.0118,"vega":0.0002,"rho":0.0,"greeksSource":"cboe","greeksMissingReason":null},{"symbol":"ABR260717P00002500","expiration":"2026-07-17","side":"put","strike":2.5,"bid":0.0,"ask":0.05,"mid":null,"last":0.02,"volume":2.0,"openInterest":1.0,"iv":3.8750003125,"delta":-0.026,"gamma":0.032,"theta":-0.0119,"vega":0.0003,"rho":0.0,"greeksSource":"cboe","greeksMissingReason":null},{"symbol":"ABR260717P00003000","expiration":"2026-07-17","side":"put","strike":3.0,"bid":0.0,"ask":0.1,"mid":null,"last":0.03,"volume":2.0,"openInterest":8.0,"iv":3.468751328125,"delta":-0.0356,"gamma":0.0537,"theta":-0.0122,"vega":0.0004,"rho":0.0,"greeksSource":"cboe","greeksMissingReason":null},{"symbol":"ABR260717P00004000","expiration":"2026-07-17","side":"put","strike":4.0,"bid":0.0,"ask":0.05,"mid":null,"last":0.05,"volume":6.0,"openInterest":13.0,"iv":1.5000025,"delta":-0.0827,"gamma":0.1988,"theta":-0.0135,"vega":0.0008,"rho":-0.0001,"greeksSource":"cboe","greeksMissingReason":null},{"symbol":"ABR260717P00004500","expiration":"2026-07-17","side":"put","strike":4.5,"bid":0.0,"ask":0.05,"mid":null,"last":0.03,"volume":1.0,"openInterest":87.0,"iv":0.85937640625,"delta":-0.1689,"gamma":0.5394,"theta":-0.0146,"vega":0.0013,"rho":-0.0001,"greeksSource":"cboe","greeksMissingReason":null},{"symbol":"ABR260717P00005000","expiration":"2026-07-17","side":"put","strike":5.0,"bid":0.05,"ask":0.2,"mid":0.125,"last":0.1,"volume":179.0,"openInterest":2026.0,"iv":0.6015664843750002,"delta":-0.6141,"gamma":1.3449,"theta":-0.0146,"vega":0.002,"rho":-0.0004,"greeksSource":"cboe","greeksMissingReason":null},{"symbol":"ABR260717P00005500","expiration":"2026-07-17","side":"put","strike":5.5,"bid":0.2,"ask":0.95,"mid":0.575,"last":0.46,"volume":1.0,"openInterest":79.0,"iv":1.140629296875,"delta":-0.8735,"gamma":0.4486,"theta":-0.0118,"vega":0.0011,"rho":-0.0004,"greeksSource":"cboe","greeksMissingReason":null},{"symbol":"ABR260717P00006000","expiration":"2026-07-17","side":"put","strike":6.0,"bid":0.85,"ask":1.3,"mid":1.075,"last":1.09,"volume":1.0,"openInterest":77.0,"iv":1.6875015625,"delta":-0.9324,"gamma":0.2115,"theta":-0.0093,"vega":0.0007,"rho":-0.0004,"greeksSource":"cboe","greeksMissingReason":null},{"symbol":"ABR260717P00006500","expiration":"2026-07-17","side":"put","strike":6.5,"bid":1.0,"ask":2.15,"mid":1.575,"last":1.37,"volume":2.0,"openInterest":0.0,"iv":2.1406296484375,"delta":-0.9572,"gamma":0.1232,"theta":-0.0075,"vega":0.0005,"rho":-0.0004,"greeksSource":"cboe","greeksMissingReason":null},{"symbol":"ABR260717P00007000","expiration":"2026-07-17","side":"put","strike":7.0,"bid":1.75,"ask":2.35,"mid":2.05,"last":2.1,"volume":24.0,"openInterest":86.0,"iv":2.281254296875,"delta":-0.9706,"gamma":0.0805,"theta":-0.006,"vega":0.0003,"rho":-0.0004,"greeksSource":"cboe","greeksMissingReason":null},{"symbol":"ABR260717P00007500","expiration":"2026-07-17","side":"put","strike":7.5,"bid":2.15,"ask":2.8,"mid":2.4749999999999996,"last":2.45,"volume":1.0,"openInterest":2.0,"iv":4.4687544140624995,"delta":-0.9789,"gamma":0.0567,"theta":-0.0048,"vega":0.0002,"rho":-0.0003,"greeksSource":"cboe","greeksMissingReason":null},{"symbol":"ABR260717P00008000","expiration":"2026-07-17","side":"put","strike":8.0,"bid":2.9,"ask":3.1,"mid":3.0,"last":3.0,"volume":4.0,"openInterest":99.0,"iv":1.000005,"delta":-0.9844,"gamma":0.0418,"theta":-0.0039,"vega":0.0002,"rho":-0.0003,"greeksSource":"cboe","greeksMissingReason":null},{"symbol":"ABR260717P00009000","expiration":"2026-07-17","side":"put","strike":9.0,"bid":3.8,"ask":4.1,"mid":3.9499999999999997,"last":3.83,"volume":1.0,"openInterest":2.0,"iv":3.99218751953125,"delta":-0.991,"gamma":0.0248,"theta":-0.0026,"vega":0.0001,"rho":-0.0002,"greeksSource":"cboe","greeksMissingReason":null},{"symbol":"ABR260717P00009500","expiration":"2026-07-17","side":"put","strike":9.5,"bid":4.2,"ask":4.6,"mid":4.4,"last":4.34,"volume":null,"openInterest":0.0,"iv":4.2500046875,"delta":-0.9932,"gamma":0.0193,"theta":-0.0022,"vega":0.0001,"rho":-0.0002,"greeksSource":"cboe","greeksMissingReason":null},{"symbol":"ABR260717P00010000","expiration":"2026-07-17","side":"put","strike":10.0,"bid":4.6,"ask":5.1,"mid":4.85,"last":5.1,"volume":4.0,"openInterest":0.0,"iv":4.4687544140624995,"delta":-0.9947,"gamma":0.0154,"theta":-0.0018,"vega":0.0001,"rho":-0.0002,"greeksSource":"cboe","greeksMissingReason":null},{"symbol":"ABR260717P00011000","expiration":"2026-07-17","side":"put","strike":11.0,"bid":2.5,"ask":3.9,"mid":3.2,"last":3.44,"volume":2.0,"openInterest":35.0,"iv":1.0000000000000003e-05,"delta":-0.9969,"gamma":0.0097,"theta":-0.0014,"vega":0.0,"rho":-0.0001,"greeksSource":"cboe","greeksMissingReason":null},{"symbol":"ABR260717P00012000","expiration":"2026-07-17","side":"put","strike":12.0,"bid":6.3,"ask":7.7,"mid":7.0,"last":7.1,"volume":4.0,"openInterest":0.0,"iv":2.000005,"delta":-0.9982,"gamma":0.0062,"theta":-0.0011,"vega":0.0,"rho":-0.0001,"greeksSource":"cboe","greeksMissingReason":null},{"symbol":"ABR260717P00013000","expiration":"2026-07-17","side":"put","strike":13.0,"bid":7.3,"ask":8.8,"mid":8.05,"last":8.1,"volume":4.0,"openInterest":3.0,"iv":4.906253867187499,"delta":-0.9989,"gamma":0.0038,"theta":-0.001,"vega":0.0,"rho":0.0,"greeksSource":"cboe","greeksMissingReason":null},{"symbol":"ABR260717P00014000","expiration":"2026-07-17","side":"put","strike":14.0,"bid":8.3,"ask":9.8,"mid":9.05,"last":9.1,"volume":4.0,"openInterest":2.0,"iv":5.187503515625,"delta":-0.9994,"gamma":0.0023,"theta":-0.0008,"vega":0.0,"rho":0.0,"greeksSource":"cboe","greeksMissingReason":null},{"symbol":"ABR260717P00015000","expiration":"2026-07-17","side":"put","strike":15.0,"bid":9.3,"ask":10.8,"mid":10.05,"last":10.1,"volume":4.0,"openInterest":1.0,"iv":5.468753164062499,"delta":-0.9996,"gamma":0.0014,"theta":-0.0008,"vega":0.0,"rho":0.0,"greeksSource":"cboe","greeksMissingReason":null},{"symbol":"ABR260717P00016000","expiration":"2026-07-17","side":"put","strike":16.0,"bid":10.1,"ask":12.0,"mid":11.05,"last":10.63,"volume":2.0,"openInterest":2.0,"iv":5.687502890625,"delta":-0.9998,"gamma":0.0008,"theta":-0.0008,"vega":0.0,"rho":0.0,"greeksSource":"cboe","greeksMissingReason":null},{"symbol":"ABR260724C00001000","expiration":"2026-07-24","side":"call","strike":1.0,"bid":3.3,"ask":4.5,"mid":3.9,"last":5.29,"volume":null,"openInterest":10.0,"iv":13.03125185546875,"delta":0.9858,"gamma":0.0081,"theta":-0.0068,"vega":0.0003,"rho":0.0003,"greeksSource":"cboe","greeksMissingReason":null},{"symbol":"ABR260724C00001500","expiration":"2026-07-24","side":"call","strike":1.5,"bid":3.4,"ask":3.7,"mid":3.55,"last":3.65,"volume":1.0,"openInterest":93.0,"iv":4.437504453124999,"delta":0.9792,"gamma":0.0147,"theta":-0.0072,"vega":0.0004,"rho":0.0005,"greeksSource":"cboe","greeksMissingReason":null},{"symbol":"ABR260724C00002000","expiration":"2026-07-24","side":"call","strike":2.0,"bid":2.35,"ask":3.3,"mid":2.825,"last":2.97,"volume":4.0,"openInterest":43.0,"iv":5.87500265625,"delta":0.9713,"gamma":0.0243,"theta":-0.0075,"vega":0.0006,"rho":0.0006,"greeksSource":"cboe","greeksMissingReason":null},{"symbol":"ABR260724C00002500","expiration":"2026-07-24","side":"call","strike":2.5,"bid":2.05,"ask":2.9,"mid":2.4749999999999996,"last":2.31,"volume":2.0,"openInterest":12.0,"iv":5.304690869140623,"delta":0.9611,"gamma":0.0395,"theta":-0.0076,"vega":0.0007,"rho":0.0008,"greeksSource":"cboe","greeksMissingReason":null},{"symbol":"ABR260724C00003000","expiration":"2026-07-24","side":"call","strike":3.0,"bid":1.55,"ask":2.3,"mid":1.9249999999999998,"last":2.02,"volume":4.0,"openInterest":12.0,"iv":3.74218814453125,"delta":0.9466,"gamma":0.065,"theta":-0.0078,"vega":0.0009,"rho":0.001,"greeksSource":"cboe","greeksMissingReason":null},{"symbol":"ABR260724C00004000","expiration":"2026-07-24","side":"call","strike":4.0,"bid":0.55,"ask":1.3,"mid":0.925,"last":1.05,"volume":44.0,"openInterest":18.0,"iv":2.2265669335937495,"delta":0.8819,"gamma":0.2139,"theta":-0.0081,"vega":0.0017,"rho":0.0012,"greeksSource":"cboe","greeksMissingReason":null},{"symbol":"ABR260724C00004500","expiration":"2026-07-24","side":"call","strike":4.5,"bid":0.1,"ask":0.85,"mid":0.475,"last":0.58,"volume":1.0,"openInterest":1.0,"iv":1.7265638671875,"delta":0.7822,"gamma":0.4897,"theta":-0.008,"vega":0.0025,"rho":0.0012,"greeksSource":"cboe","greeksMissingReason":null},{"symbol":"ABR260724C00005000","expiration":"2026-07-24","side":"call","strike":5.0,"bid":0.1,"ask":0.25,"mid":0.175,"last":0.17,"volume":27.0,"openInterest":51.0,"iv":0.507817421875,"delta":0.4311,"gamma":1.0004,"theta":-0.0071,"vega":0.0034,"rho":0.0007,"greeksSource":"cboe","greeksMissingReason":null},{"symbol":"ABR260724C00005500","expiration":"2026-07-24","side":"call","strike":5.5,"bid":0.0,"ask":0.05,"mid":null,"last":0.03,"volume":1.0,"openInterest":507.0,"iv":0.585941640625,"delta":0.1722,"gamma":0.4637,"theta":-0.0063,"vega":0.0022,"rho":0.0003,"greeksSource":"cboe","greeksMissingReason":null},{"symbol":"ABR260724C00006000","expiration":"2026-07-24","side":"call","strike":6.0,"bid":0.0,"ask":0.05,"mid":null,"last":0.03,"volume":119.0,"openInterest":393.0,"iv":0.7421900781249999,"delta":0.1003,"gamma":0.2432,"theta":-0.0055,"vega":0.0015,"rho":0.0002,"greeksSource":"cboe","greeksMissingReason":null},{"symbol":"ABR260724C00006500","expiration":"2026-07-24","side":"call","strike":6.5,"bid":0.0,"ask":0.05,"mid":null,"last":0.04,"volume":1.0,"openInterest":3.0,"iv":0.9687503125,"delta":0.0682,"gamma":0.1513,"theta":-0.0049,"vega":0.0011,"rho":0.0001,"greeksSource":"cboe","greeksMissingReason":null},{"symbol":"ABR260724C00008000","expiration":"2026-07-24","side":"call","strike":8.0,"bid":null,"ask":0.25,"mid":null,"last":0.05,"volume":2.0,"openInterest":2.0,"iv":2.7343781640625,"delta":0.0312,"gamma":0.0582,"theta":-0.0035,"vega":0.0006,"rho":0.0,"greeksSource":"cboe","greeksMissingReason":null},{"symbol":"ABR260724P00001000","expiration":"2026-07-24","side":"put","strike":1.0,"bid":null,"ask":0.4,"mid":null,"last":0.05,"volume":null,"openInterest":null,"iv":11.53125279296875,"delta":-0.0146,"gamma":0.0081,"theta":-0.0072,"vega":0.0003,"rho":0.0,"greeksSource":"cboe","greeksMissingReason":null},{"symbol":"ABR260724P00001500","expiration":"2026-07-24","side":"put","strike":1.5,"bid":0.0,"ask":0.2,"mid":null,"last":0.05,"volume":4.0,"openInterest":5.0,"iv":5.23437845703125,"delta":-0.0213,"gamma":0.0147,"theta":-0.0076,"vega":0.0004,"rho":0.0,"greeksSource":"cboe","greeksMissingReason":null},{"symbol":"ABR260724P00002000","expiration":"2026-07-24","side":"put","strike":2.0,"bid":0.0,"ask":0.2,"mid":null,"last":0.05,"volume":2.0,"openInterest":1.0,"iv":4.0937548828125,"delta":-0.0291,"gamma":0.0244,"theta":-0.0078,"vega":0.0006,"rho":-0.0001,"greeksSource":"cboe","greeksMissingReason":null},{"symbol":"ABR260724P00002500","expiration":"2026-07-24","side":"put","strike":2.5,"bid":0.0,"ask":0.75,"mid":null,"last":0.05,"volume":4.0,"openInterest":2.0,"iv":5.1562535546875,"delta":-0.0393,"gamma":0.0395,"theta":-0.0079,"vega":0.0007,"rho":-0.0001,"greeksSource":"cboe","greeksMissingReason":null},{"symbol":"ABR260724P00003000","expiration":"2026-07-24","side":"put","strike":3.0,"bid":0.0,"ask":0.75,"mid":null,"last":0.05,"volume":null,"openInterest":2.0,"iv":4.1328173339843755,"delta":-0.0539,"gamma":0.065,"theta":-0.008,"vega":0.0009,"rho":-0.0001,"greeksSource":"cboe","greeksMissingReason":null},{"symbol":"ABR260724P00003500","expiration":"2026-07-24","side":"put","strike":3.5,"bid":0.0,"ask":0.55,"mid":null,"last":0.05,"volume":2.0,"openInterest":2.0,"iv":2.8281279296874997,"delta":-0.0768,"gamma":0.1124,"theta":-0.0081,"vega":0.0012,"rho":-0.0001,"greeksSource":"cboe","greeksMissingReason":null},{"symbol":"ABR260724P00004000","expiration":"2026-07-24","side":"put","strike":4.0,"bid":0.0,"ask":0.05,"mid":null,"last":0.03,"volume":400.0,"openInterest":432.0,"iv":0.9062509375,"delta":-0.1187,"gamma":0.2144,"theta":-0.0082,"vega":0.0017,"rho":-0.0002,"greeksSource":"cboe","greeksMissingReason":null},{"symbol":"ABR260724P00004500","expiration":"2026-07-24","side":"put","strike":4.5,"bid":0.0,"ask":0.1,"mid":null,"last":0.05,"volume":1.0,"openInterest":175.0,"iv":0.648441015625,"delta":-0.219,"gamma":0.4918,"theta":-0.0081,"vega":0.0025,"rho":-0.0004,"greeksSource":"cboe","greeksMissingReason":null},{"symbol":"ABR260724P00005000","expiration":"2026-07-24","side":"put","strike":5.0,"bid":0.05,"ask":0.2,"mid":0.125,"last":0.13,"volume":3.0,"openInterest":547.0,"iv":0.57812921875,"delta":-0.5734,"gamma":1.0091,"theta":-0.0072,"vega":0.0033,"rho":-0.0008,"greeksSource":"cboe","greeksMissingReason":null},{"symbol":"ABR260724P00005500","expiration":"2026-07-24","side":"put","strike":5.5,"bid":0.25,"ask":1.0,"mid":0.625,"last":0.53,"volume":2.0,"openInterest":2.0,"iv":0.867188828125,"delta":-0.8332,"gamma":0.4701,"theta":-0.0063,"vega":0.0021,"rho":-0.001,"greeksSource":"cboe","greeksMissingReason":null},{"symbol":"ABR260724P00006000","expiration":"2026-07-24","side":"put","strike":6.0,"bid":0.75,"ask":1.45,"mid":1.1,"last":1.0,"volume":null,"openInterest":18.0,"iv":1.125004375,"delta":-0.9049,"gamma":0.2482,"theta":-0.0055,"vega":0.0014,"rho":-0.001,"greeksSource":"cboe","greeksMissingReason":null},{"symbol":"ABR260724P00006500","expiration":"2026-07-24","side":"put","strike":6.5,"bid":1.2,"ask":1.95,"mid":1.575,"last":1.34,"volume":null,"openInterest":0.0,"iv":1.2890660546875,"delta":-0.9368,"gamma":0.1552,"theta":-0.0049,"vega":0.001,"rho":-0.001,"greeksSource":"cboe","greeksMissingReason":null},{"symbol":"ABR260724P00007000","expiration":"2026-07-24","side":"put","strike":7.0,"bid":1.75,"ask":2.45,"mid":2.1,"last":2.11,"volume":20.0,"openInterest":21.0,"iv":1.65625171875,"delta":-0.9546,"gamma":0.107,"theta":-0.0043,"vega":0.0008,"rho":-0.0009,"greeksSource":"cboe","greeksMissingReason":null},{"symbol":"ABR260724P00007500","expiration":"2026-07-24","side":"put","strike":7.5,"bid":2.0,"ask":3.2,"mid":2.6,"last":2.31,"volume":null,"openInterest":0.0,"iv":1.875000625,"delta":-0.966,"gamma":0.0793,"theta":-0.0038,"vega":0.0006,"rho":-0.0009,"greeksSource":"cboe","greeksMissingReason":null},{"symbol":"ABR260724P00008000","expiration":"2026-07-24","side":"put","strike":8.0,"bid":2.5,"ask":4.3,"mid":3.4,"last":2.9,"volume":12.0,"openInterest":8.0,"iv":3.2656268359375,"delta":-0.9738,"gamma":0.061,"theta":-0.0033,"vega":0.0005,"rho":-0.0008,"greeksSource":"cboe","greeksMissingReason":null},{"symbol":"ABR260724P00009000","expiration":"2026-07-24","side":"put","strike":9.0,"bid":3.5,"ask":5.4,"mid":4.45,"last":3.9,"volume":4.0,"openInterest":1.0,"iv":3.843750390625,"delta":-0.9839,"gamma":0.0406,"theta":-0.0026,"vega":0.0003,"rho":-0.0007,"greeksSource":"cboe","greeksMissingReason":null},{"symbol":"ABR260731C00001000","expiration":"2026-07-31","side":"call","strike":1.0,"bid":3.3,"ask":4.5,"mid":3.9,"last":4.05,"volume":31.0,"openInterest":197.0,"iv":10.1875036328125,"delta":0.986,"gamma":0.0082,"theta":-0.0041,"vega":0.0004,"rho":0.0005,"greeksSource":"cboe","greeksMissingReason":null},{"symbol":"ABR260731C00001500","expiration":"2026-07-31","side":"call","strike":1.5,"bid":2.8,"ask":4.0,"mid":3.4,"last":4.7,"volume":20.0,"openInterest":162.0,"iv":7.37500078125,"delta":0.979,"gamma":0.0148,"theta":-0.0044,"vega":0.0006,"rho":0.0007,"greeksSource":"cboe","greeksMissingReason":null},{"symbol":"ABR260731C00002000","expiration":"2026-07-31","side":"call","strike":2.0,"bid":2.3,"ask":3.5,"mid":2.9,"last":3.1,"volume":4.0,"openInterest":16.0,"iv":5.7500028125,"delta":0.9705,"gamma":0.0248,"theta":-0.0047,"vega":0.0007,"rho":0.001,"greeksSource":"cboe","greeksMissingReason":null},{"symbol":"ABR260731C00002500","expiration":"2026-07-31","side":"call","strike":2.5,"bid":2.0,"ask":3.2,"mid":2.6,"last":2.6,"volume":null,"openInterest":3.0,"iv":2.5156287109374995,"delta":0.9592,"gamma":0.0404,"theta":-0.005,"vega":0.001,"rho":0.0012,"greeksSource":"cboe","greeksMissingReason":null},{"symbol":"ABR260731C00003000","expiration":"2026-07-31","side":"call","strike":3.0,"bid":1.55,"ask":2.3,"mid":1.9249999999999998,"last":2.01,"volume":28.0,"openInterest":8.0,"iv":2.9218776953125003,"delta":0.9428,"gamma":0.0667,"theta":-0.0052,"vega":0.0013,"rho":0.0015,"greeksSource":"cboe","greeksMissingReason":null},{"symbol":"ABR260731C00004000","expiration":"2026-07-31","side":"call","strike":4.0,"bid":0.6,"ask":1.3,"mid":0.95,"last":1.1,"volume":20.0,"openInterest":5.0,"iv":1.7421887890624999,"delta":0.8694,"gamma":0.214,"theta":-0.0057,"vega":0.0023,"rho":0.0018,"greeksSource":"cboe","greeksMissingReason":null},{"symbol":"ABR260731C00005000","expiration":"2026-07-31","side":"call","strike":5.0,"bid":0.15,"ask":0.35,"mid":0.25,"last":0.27,"volume":17.0,"openInterest":147.0,"iv":0.5625043750000001,"delta":0.4567,"gamma":0.8095,"theta":-0.0054,"vega":0.0043,"rho":0.0011,"greeksSource":"cboe","greeksMissingReason":null},{"symbol":"ABR260731C00005500","expiration":"2026-07-31","side":"call","strike":5.5,"bid":0.0,"ask":0.1,"mid":null,"last":0.07,"volume":15.0,"openInterest":705.0,"iv":0.6093789062500001,"delta":0.1989,"gamma":0.4645,"theta":-0.0046,"vega":0.0031,"rho":0.0005,"greeksSource":"cboe","greeksMissingReason":null},{"symbol":"ABR260731C00006000","expiration":"2026-07-31","side":"call","strike":6.0,"bid":0.0,"ask":0.05,"mid":null,"last":0.05,"volume":10.0,"openInterest":121.0,"iv":0.57812921875,"delta":0.1135,"gamma":0.2541,"theta":-0.0039,"vega":0.0021,"rho":0.0003,"greeksSource":"cboe","greeksMissingReason":null},{"symbol":"ABR260731C00006500","expiration":"2026-07-31","side":"call","strike":6.5,"bid":0.0,"ask":1.0,"mid":null,"last":0.01,"volume":1.0,"openInterest":11.0,"iv":2.1718795703125,"delta":0.0753,"gamma":0.1588,"theta":-0.0034,"vega":0.0016,"rho":0.0002,"greeksSource":"cboe","greeksMissingReason":null},{"symbol":"ABR260731C00008000","expiration":"2026-07-31","side":"call","strike":8.0,"bid":null,"ask":0.1,"mid":null,"last":0.05,"volume":null,"openInterest":3.0,"iv":1.6171894140625,"delta":0.0324,"gamma":0.0597,"theta":-0.0023,"vega":0.0008,"rho":0.0001,"greeksSource":"cboe","greeksMissingReason":null},{"symbol":"ABR260731P00001000","expiration":"2026-07-31","side":"put","strike":1.0,"bid":0.0,"ask":0.2,"mid":null,"last":0.05,"volume":2.0,"openInterest":3.0,"iv":5.437503203124999,"delta":-0.0148,"gamma":0.0082,"theta":-0.0046,"vega":0.0004,"rho":0.0,"greeksSource":"cboe","greeksMissingReason":null},{"symbol":"ABR260731P00001500","expiration":"2026-07-31","side":"put","strike":1.5,"bid":0.0,"ask":0.75,"mid":null,"last":0.05,"volume":2.0,"openInterest":1.0,"iv":6.437501953125,"delta":-0.0218,"gamma":0.0149,"theta":-0.0049,"vega":0.0006,"rho":-0.0001,"greeksSource":"cboe","greeksMissingReason":null},{"symbol":"ABR260731P00002000","expiration":"2026-07-31","side":"put","strike":2.0,"bid":0.0,"ask":0.75,"mid":null,"last":0.05,"volume":null,"openInterest":1.0,"iv":5.039066201171874,"delta":-0.0303,"gamma":0.0248,"theta":-0.0051,"vega":0.0007,"rho":-0.0001,"greeksSource":"cboe","greeksMissingReason":null},{"symbol":"ABR260731P00002500","expiration":"2026-07-31","side":"put","strike":2.5,"bid":0.0,"ask":0.75,"mid":null,"last":0.05,"volume":8.0,"openInterest":6.0,"iv":4.0312549609375,"delta":-0.0417,"gamma":0.0405,"theta":-0.0053,"vega":0.001,"rho":-0.0001,"greeksSource":"cboe","greeksMissingReason":null},{"symbol":"ABR260731P00003000","expiration":"2026-07-31","side":"put","strike":3.0,"bid":0.0,"ask":0.75,"mid":null,"last":0.08,"volume":12.0,"openInterest":2.0,"iv":3.2343769140624996,"delta":-0.058,"gamma":0.0668,"theta":-0.0055,"vega":0.0013,"rho":-0.0002,"greeksSource":"cboe","greeksMissingReason":null},{"symbol":"ABR260731P00003500","expiration":"2026-07-31","side":"put","strike":3.5,"bid":0.0,"ask":0.75,"mid":null,"last":0.2,"volume":1.0,"openInterest":2.0,"iv":2.56250359375,"delta":-0.0841,"gamma":0.115,"theta":-0.0056,"vega":0.0017,"rho":-0.0002,"greeksSource":"cboe","greeksMissingReason":null},{"symbol":"ABR260731P00004000","expiration":"2026-07-31","side":"put","strike":4.0,"bid":0.0,"ask":0.75,"mid":null,"last":0.05,"volume":2.0,"openInterest":18.0,"iv":1.96875015625,"delta":-0.1318,"gamma":0.2147,"theta":-0.0058,"vega":0.0023,"rho":-0.0004,"greeksSource":"cboe","greeksMissingReason":null},{"symbol":"ABR260731P00004500","expiration":"2026-07-31","side":"put","strike":4.5,"bid":0.0,"ask":0.1,"mid":null,"last":0.1,"volume":4.0,"openInterest":31.0,"iv":0.507817421875,"delta":-0.2408,"gamma":0.4561,"theta":-0.0059,"vega":0.0034,"rho":-0.0006,"greeksSource":"cboe","greeksMissingReason":null},{"symbol":"ABR260731P00005000","expiration":"2026-07-31","side":"put","strike":5.0,"bid":0.15,"ask":0.25,"mid":0.2,"last":0.25,"volume":157.0,"openInterest":270.0,"iv":0.5664105859375,"delta":-0.5489,"gamma":0.8198,"theta":-0.0055,"vega":0.0043,"rho":-0.0012,"greeksSource":"cboe","greeksMissingReason":null},{"symbol":"ABR260731P00005500","expiration":"2026-07-31","side":"put","strike":5.5,"bid":0.25,"ask":1.0,"mid":0.625,"last":0.5,"volume":150.0,"openInterest":212.0,"iv":0.6757844921875001,"delta":-0.8094,"gamma":0.4745,"theta":-0.0046,"vega":0.003,"rho":-0.0016,"greeksSource":"cboe","greeksMissingReason":null},{"symbol":"ABR260731P00006000","expiration":"2026-07-31","side":"put","strike":6.0,"bid":0.75,"ask":1.45,"mid":1.1,"last":1.1,"volume":20.0,"openInterest":15.0,"iv":0.87500125,"delta":-0.8952,"gamma":0.2626,"theta":-0.0039,"vega":0.002,"rho":-0.0015,"greeksSource":"cboe","greeksMissingReason":null},{"symbol":"ABR260731P00006500","expiration":"2026-07-31","side":"put","strike":6.5,"bid":1.2,"ask":1.95,"mid":1.575,"last":1.25,"volume":null,"openInterest":1.0,"iv":1.0078174609375,"delta":-0.9333,"gamma":0.1659,"theta":-0.0033,"vega":0.0014,"rho":-0.0014,"greeksSource":"cboe","greeksMissingReason":null},{"symbol":"ABR260731P00007000","expiration":"2026-07-31","side":"put","strike":7.0,"bid":1.7,"ask":2.45,"mid":2.075,"last":1.9,"volume":4.0,"openInterest":8.0,"iv":1.1875040625,"delta":-0.9544,"gamma":0.1146,"theta":-0.0029,"vega":0.001,"rho":-0.0013,"greeksSource":"cboe","greeksMissingReason":null},{"symbol":"ABR260731P00007500","expiration":"2026-07-31","side":"put","strike":7.5,"bid":2.0,"ask":3.2,"mid":2.6,"last":2.28,"volume":null,"openInterest":0.0,"iv":1.4609401953124999,"delta":-0.9677,"gamma":0.0844,"theta":-0.0024,"vega":0.0008,"rho":-0.0012,"greeksSource":"cboe","greeksMissingReason":null},{"symbol":"ABR260731P00008000","expiration":"2026-07-31","side":"put","strike":8.0,"bid":2.5,"ask":3.7,"mid":3.1,"last":3.0,"volume":8.0,"openInterest":12.0,"iv":1.6171894140625,"delta":-0.9768,"gamma":0.0659,"theta":-0.0021,"vega":0.0006,"rho":-0.0011,"greeksSource":"cboe","greeksMissingReason":null},{"symbol":"ABR260731P00009000","expiration":"2026-07-31","side":"put","strike":9.0,"bid":3.5,"ask":4.7,"mid":4.1,"last":3.85,"volume":16.0,"openInterest":0.0,"iv":1.8828130859374999,"delta":-0.9881,"gamma":0.0421,"theta":-0.0015,"vega":0.0003,"rho":-0.0007,"greeksSource":"cboe","greeksMissingReason":null},{"symbol":"ABR260731P00009500","expiration":"2026-07-31","side":"put","strike":9.5,"bid":4.0,"ask":5.2,"mid":4.6,"last":4.15,"volume":null,"openInterest":0.0,"iv":2.000005,"delta":-0.9917,"gamma":0.0339,"theta":-0.0012,"vega":0.0003,"rho":-0.0007,"greeksSource":"cboe","greeksMissingReason":null},{"symbol":"ABR260807C00001000","expiration":"2026-08-07","side":"call","strike":1.0,"bid":3.5,"ask":6.0,"mid":4.75,"last":5.0,"volume":20.0,"openInterest":167.0,"iv":11.812502617187501,"delta":0.9821,"gamma":0.0092,"theta":-0.0038,"vega":0.0006,"rho":0.0006,"greeksSource":"cboe","greeksMissingReason":null},{"symbol":"ABR260807C00001500","expiration":"2026-08-07","side":"call","strike":1.5,"bid":2.25,"ask":4.3,"mid":3.275,"last":3.7,"volume":33.0,"openInterest":120.0,"iv":8.281254824218749,"delta":0.973,"gamma":0.0167,"theta":-0.0042,"vega":0.0008,"rho":0.001,"greeksSource":"cboe","greeksMissingReason":null},{"symbol":"ABR260807C00002000","expiration":"2026-08-07","side":"call","strike":2.0,"bid":2.35,"ask":3.9,"mid":3.125,"last":2.3,"volume":null,"openInterest":20.0,"iv":2.8906277734375,"delta":0.9623,"gamma":0.0276,"theta":-0.0045,"vega":0.0011,"rho":0.0013,"greeksSource":"cboe","greeksMissingReason":null},{"symbol":"ABR260807C00004000","expiration":"2026-08-07","side":"call","strike":4.0,"bid":0.6,"ask":1.35,"mid":0.9750000000000001,"last":1.07,"volume":null,"openInterest":3.0,"iv":1.60547072265625,"delta":0.8477,"gamma":0.2112,"theta":-0.0051,"vega":0.003,"rho":0.0023,"greeksSource":"cboe","greeksMissingReason":null},{"symbol":"ABR260807C00005000","expiration":"2026-08-07","side":"call","strike":5.0,"bid":0.2,"ask":0.3,"mid":0.25,"last":0.27,"volume":6.0,"openInterest":155.0,"iv":0.5742230078125,"delta":0.4732,"gamma":0.6799,"theta":-0.0046,"vega":0.0051,"rho":0.0016,"greeksSource":"cboe","greeksMissingReason":null},{"symbol":"ABR260807C00005500","expiration":"2026-08-07","side":"call","strike":5.5,"bid":0.05,"ask":0.15,"mid":0.1,"last":0.07,"volume":51.0,"openInterest":166.0,"iv":0.51562984375,"delta":0.2373,"gamma":0.4483,"theta":-0.0042,"vega":0.004,"rho":0.0008,"greeksSource":"cboe","greeksMissingReason":null},{"symbol":"ABR260807C00006000","expiration":"2026-08-07","side":"call","strike":6.0,"bid":0.0,"ask":0.15,"mid":null,"last":0.15,"volume":1.0,"openInterest":224.0,"iv":0.6718782812500002,"delta":0.147,"gamma":0.2699,"theta":-0.0038,"vega":0.003,"rho":0.0005,"greeksSource":"cboe","greeksMissingReason":null},{"symbol":"ABR260807C00006500","expiration":"2026-08-07","side":"call","strike":6.5,"bid":0.0,"ask":0.95,"mid":null,"last":0.13,"volume":null,"openInterest":2.0,"iv":1.79296978515625,"delta":0.1037,"gamma":0.1802,"theta":-0.0035,"vega":0.0023,"rho":0.0003,"greeksSource":"cboe","greeksMissingReason":null},{"symbol":"ABR260807C00008000","expiration":"2026-08-07","side":"call","strike":8.0,"bid":null,"ask":0.75,"mid":null,"last":0.42,"volume":null,"openInterest":1.0,"iv":2.8906277734375,"delta":0.0508,"gamma":0.0776,"theta":-0.0027,"vega":0.0013,"rho":0.0002,"greeksSource":"cboe","greeksMissingReason":null},{"symbol":"ABR260807P00001000","expiration":"2026-08-07","side":"put","strike":1.0,"bid":0.0,"ask":0.2,"mid":null,"last":0.1,"volume":null,"openInterest":2.0,"iv":4.5937542578125,"delta":-0.0185,"gamma":0.0092,"theta":-0.0044,"vega":0.0006,"rho":-0.0001,"greeksSource":"cboe","greeksMissingReason":null},{"symbol":"ABR260807P00001500","expiration":"2026-08-07","side":"put","strike":1.5,"bid":0.0,"ask":0.75,"mid":null,"last":0.05,"volume":4.0,"openInterest":1.0,"iv":5.460940673828125,"delta":-0.0276,"gamma":0.0167,"theta":-0.0048,"vega":0.0008,"rho":-0.0001,"greeksSource":"cboe","greeksMissingReason":null},{"symbol":"ABR260807P00002000","expiration":"2026-08-07","side":"put","strike":2.0,"bid":0.0,"ask":0.75,"mid":null,"last":0.05,"volume":2.0,"openInterest":0.0,"iv":4.273442158203125,"delta":-0.0384,"gamma":0.0276,"theta":-0.0049,"vega":0.0011,"rho":-0.0002,"greeksSource":"cboe","greeksMissingReason":null},{"symbol":"ABR260807P00002500","expiration":"2026-08-07","side":"put","strike":2.5,"bid":0.0,"ask":0.75,"mid":null,"last":0.05,"volume":2.0,"openInterest":4.0,"iv":3.4218764453125,"delta":-0.0523,"gamma":0.0444,"theta":-0.0051,"vega":0.0014,"rho":-0.0002,"greeksSource":"cboe","greeksMissingReason":null},{"symbol":"ABR260807P00003000","expiration":"2026-08-07","side":"put","strike":3.0,"bid":0.0,"ask":0.75,"mid":null,"last":0.08,"volume":2.0,"openInterest":2.0,"iv":2.74219064453125,"delta":-0.0718,"gamma":0.0716,"theta":-0.0052,"vega":0.0018,"rho":-0.0003,"greeksSource":"cboe","greeksMissingReason":null},{"symbol":"ABR260807P00003500","expiration":"2026-08-07","side":"put","strike":3.5,"bid":0.0,"ask":0.75,"mid":null,"last":0.09,"volume":2.0,"openInterest":1.0,"iv":2.1718795703125,"delta":-0.1017,"gamma":0.1192,"theta":-0.0052,"vega":0.0023,"rho":-0.0004,"greeksSource":"cboe","greeksMissingReason":null},{"symbol":"ABR260807P00004500","expiration":"2026-08-07","side":"put","strike":4.5,"bid":0.0,"ask":0.75,"mid":null,"last":0.1,"volume":6.0,"openInterest":62.0,"iv":1.19922275390625,"delta":-0.2627,"gamma":0.4151,"theta":-0.0051,"vega":0.0042,"rho":-0.0009,"greeksSource":"cboe","greeksMissingReason":null},{"symbol":"ABR260807P00005000","expiration":"2026-08-07","side":"put","strike":5.0,"bid":0.2,"ask":0.3,"mid":0.25,"last":0.3,"volume":8.0,"openInterest":8.0,"iv":0.5742230078125,"delta":-0.5321,"gamma":0.689,"theta":-0.0047,"vega":0.0051,"rho":-0.0017,"greeksSource":"cboe","greeksMissingReason":null},{"symbol":"ABR260807P00005500","expiration":"2026-08-07","side":"put","strike":5.5,"bid":0.0,"ask":2.7,"mid":null,"last":0.36,"volume":null,"openInterest":1.0,"iv":1.99609376953125,"delta":-0.7709,"gamma":0.4584,"theta":-0.0042,"vega":0.0039,"rho":-0.0021,"greeksSource":"cboe","greeksMissingReason":null},{"symbol":"ABR260807P00007500","expiration":"2026-08-07","side":"put","strike":7.5,"bid":1.8,"ask":4.6,"mid":3.1999999999999997,"last":2.33,"volume":null,"openInterest":0.0,"iv":2.6289096777343754,"delta":-0.9472,"gamma":0.1049,"theta":-0.0027,"vega":0.0013,"rho":-0.002,"greeksSource":"cboe","greeksMissingReason":null},{"symbol":"ABR260807P00009500","expiration":"2026-08-07","side":"put","strike":9.5,"bid":3.3,"ask":6.6,"mid":4.949999999999999,"last":4.2,"volume":null,"openInterest":0.0,"iv":2.6718783203125005,"delta":-0.9796,"gamma":0.0509,"theta":-0.0017,"vega":0.0006,"rho":-0.0015,"greeksSource":"cboe","greeksMissingReason":null},{"symbol":"ABR260814C00001000","expiration":"2026-08-14","side":"call","strike":1.0,"bid":3.4,"ask":5.5,"mid":4.45,"last":4.7,"volume":10.0,"openInterest":110.0,"iv":7.187501015625001,"delta":0.9887,"gamma":0.0067,"theta":-0.0019,"vega":0.0004,"rho":0.0008,"greeksSource":"cboe","greeksMissingReason":null},{"symbol":"ABR260814C00002000","expiration":"2026-08-14","side":"call","strike":2.0,"bid":2.35,"ask":3.3,"mid":2.825,"last":3.07,"volume":null,"openInterest":20.0,"iv":3.44531388671875,"delta":0.9706,"gamma":0.0239,"theta":-0.0027,"vega":0.001,"rho":0.0015,"greeksSource":"cboe","greeksMissingReason":null},{"symbol":"ABR260814C00004000","expiration":"2026-08-14","side":"call","strike":4.0,"bid":0.45,"ask":1.5,"mid":0.975,"last":1.13,"volume":null,"openInterest":21.0,"iv":1.74609501953125,"delta":0.8634,"gamma":0.2104,"theta":-0.0035,"vega":0.003,"rho":0.0028,"greeksSource":"cboe","greeksMissingReason":null},{"symbol":"ABR260814C00005000","expiration":"2026-08-14","side":"call","strike":5.0,"bid":0.2,"ask":0.6,"mid":0.4,"last":0.18,"volume":3.0,"openInterest":17.0,"iv":0.6796907031250001,"delta":0.4847,"gamma":0.6118,"theta":-0.0041,"vega":0.0056,"rho":0.0019,"greeksSource":"cboe","greeksMissingReason":null},{"symbol":"ABR260814C00006000","expiration":"2026-08-14","side":"call","strike":6.0,"bid":null,"ask":0.3,"mid":null,"last":0.05,"volume":2.0,"openInterest":17.0,"iv":1.0664109179687502,"delta":0.1787,"gamma":0.2773,"theta":-0.0039,"vega":0.0038,"rho":0.0007,"greeksSource":"cboe","greeksMissingReason":null},{"symbol":"ABR260814C00007000","expiration":"2026-08-14","side":"call","strike":7.0,"bid":null,"ask":0.75,"mid":null,"last":0.1,"volume":null,"openInterest":1.0,"iv":2.2460981347656244,"delta":0.0975,"gamma":0.143,"theta":-0.0032,"vega":0.0023,"rho":0.0003,"greeksSource":"cboe","greeksMissingReason":null},{"symbol":"ABR260814P00001000","expiration":"2026-08-14","side":"put","strike":1.0,"bid":0.0,"ask":0.75,"mid":null,"last":0.05,"volume":2.0,"openInterest":null,"iv":6.54687681640625,"delta":-0.02,"gamma":0.0102,"theta":-0.0036,"vega":0.0007,"rho":-0.0001,"greeksSource":"cboe","greeksMissingReason":null},{"symbol":"ABR260814P00002000","expiration":"2026-08-14","side":"put","strike":2.0,"bid":null,"ask":0.75,"mid":null,"last":0.08,"volume":null,"openInterest":null,"iv":5.382815771484374,"delta":-0.0428,"gamma":0.0313,"theta":-0.0041,"vega":0.0013,"rho":-0.0002,"greeksSource":"cboe","greeksMissingReason":null},{"symbol":"ABR260814P00005000","expiration":"2026-08-14","side":"put","strike":5.0,"bid":0.0,"ask":0.6,"mid":null,"last":0.36,"volume":5.0,"openInterest":397.0,"iv":0.507817421875,"delta":-0.6117,"gamma":0.582,"theta":-0.0039,"vega":0.0054,"rho":-0.0032,"greeksSource":"cboe","greeksMissingReason":null},{"symbol":"ABR260814P00006000","expiration":"2026-08-14","side":"put","strike":6.0,"bid":0.2,"ask":3.3,"mid":1.75,"last":1.2,"volume":null,"openInterest":1.0,"iv":1.8496101269531249,"delta":-0.854,"gamma":0.2416,"theta":-0.0032,"vega":0.0032,"rho":-0.0051,"greeksSource":"cboe","greeksMissingReason":null},{"symbol":"ABR260821C00001000","expiration":"2026-08-21","side":"call","strike":1.0,"bid":3.4,"ask":4.6,"mid":4.0,"last":4.05,"volume":10.0,"openInterest":20.0,"iv":0.500005,"delta":0.9926,"gamma":0.0054,"theta":-0.001,"vega":0.0004,"rho":0.0008,"greeksSource":"cboe","greeksMissingReason":null},{"symbol":"ABR260821C00003000","expiration":"2026-08-21","side":"call","strike":3.0,"bid":0.0,"ask":0.0,"mid":null,"last":2.69,"volume":2.0,"openInterest":0.0,"iv":1.0000000000000003e-05,"delta":0.9493,"gamma":0.0632,"theta":-0.0024,"vega":0.0015,"rho":0.0023,"greeksSource":"cboe","greeksMissingReason":null},{"symbol":"ABR260821C00004000","expiration":"2026-08-21","side":"call","strike":4.0,"bid":0.6,"ask":1.35,"mid":0.9750000000000001,"last":0.99,"volume":3.0,"openInterest":59.0,"iv":1.2851598242187499,"delta":0.8701,"gamma":0.2126,"theta":-0.0031,"vega":0.0031,"rho":0.0028,"greeksSource":"cboe","greeksMissingReason":null},{"symbol":"ABR260821C00005000","expiration":"2026-08-21","side":"call","strike":5.0,"bid":0.25,"ask":0.35,"mid":0.3,"last":0.31,"volume":64.0,"openInterest":684.0,"iv":0.5371140039062501,"delta":0.4851,"gamma":0.5958,"theta":-0.004,"vega":0.006,"rho":0.0019,"greeksSource":"cboe","greeksMissingReason":null},{"symbol":"ABR260821C00006000","expiration":"2026-08-21","side":"call","strike":6.0,"bid":0.0,"ask":0.1,"mid":null,"last":0.05,"volume":29.0,"openInterest":1372.0,"iv":0.5976602734375001,"delta":0.1724,"gamma":0.2731,"theta":-0.0033,"vega":0.004,"rho":0.0008,"greeksSource":"cboe","greeksMissingReason":null},{"symbol":"ABR260821C00007000","expiration":"2026-08-21","side":"call","strike":7.0,"bid":0.0,"ask":0.05,"mid":null,"last":0.03,"volume":29.0,"openInterest":2063.0,"iv":0.6250037500000001,"delta":0.0916,"gamma":0.1376,"theta":-0.0026,"vega":0.0025,"rho":0.0004,"greeksSource":"cboe","greeksMissingReason":null},{"symbol":"ABR260821C00008000","expiration":"2026-08-21","side":"call","strike":8.0,"bid":0.0,"ask":0.05,"mid":null,"last":0.05,"volume":1.0,"openInterest":565.0,"iv":0.8125018749999999,"delta":0.0588,"gamma":0.0836,"theta":-0.0021,"vega":0.0018,"rho":0.0003,"greeksSource":"cboe","greeksMissingReason":null},{"symbol":"ABR260821C00009000","expiration":"2026-08-21","side":"call","strike":9.0,"bid":0.0,"ask":0.1,"mid":null,"last":0.05,"volume":1.0,"openInterest":1301.0,"iv":1.09375453125,"delta":0.0416,"gamma":0.0566,"theta":-0.0017,"vega":0.0014,"rho":0.0002,"greeksSource":"cboe","greeksMissingReason":null},{"symbol":"ABR260821C00010000","expiration":"2026-08-21","side":"call","strike":10.0,"bid":0.0,"ask":0.3,"mid":null,"last":0.01,"volume":2.0,"openInterest":3277.0,"iv":1.5859395703124997,"delta":0.0312,"gamma":0.0411,"theta":-0.0015,"vega":0.0011,"rho":0.0001,"greeksSource":"cboe","greeksMissingReason":null},{"symbol":"ABR260821C00011000","expiration":"2026-08-21","side":"call","strike":11.0,"bid":0.0,"ask":0.3,"mid":null,"last":0.05,"volume":2.0,"openInterest":582.0,"iv":1.7265638671875,"delta":0.0244,"gamma":0.0312,"theta":-0.0013,"vega":0.0009,"rho":0.0001,"greeksSource":"cboe","greeksMissingReason":null},{"symbol":"ABR260821C00012000","expiration":"2026-08-21","side":"call","strike":12.0,"bid":0.0,"ask":0.15,"mid":null,"last":0.05,"volume":1.0,"openInterest":47.0,"iv":1.5937520312499998,"delta":0.0196,"gamma":0.0246,"theta":-0.0011,"vega":0.0007,"rho":0.0001,"greeksSource":"cboe","greeksMissingReason":null},{"symbol":"ABR260821C00013000","expiration":"2026-08-21","side":"call","strike":13.0,"bid":0.0,"ask":0.05,"mid":null,"last":0.06,"volume":20.0,"openInterest":5257.0,"iv":1.40625296875,"delta":0.0161,"gamma":0.0198,"theta":-0.001,"vega":0.0006,"rho":0.0001,"greeksSource":"cboe","greeksMissingReason":null},{"symbol":"ABR260821C00015000","expiration":"2026-08-21","side":"call","strike":15.0,"bid":0.0,"ask":0.1,"mid":null,"last":0.1,"volume":1.0,"openInterest":3272.0,"iv":1.75000125,"delta":0.0114,"gamma":0.0136,"theta":-0.0008,"vega":0.0004,"rho":0.0,"greeksSource":"cboe","greeksMissingReason":null},{"symbol":"ABR260821C00017000","expiration":"2026-08-21","side":"call","strike":17.0,"bid":0.0,"ask":0.0,"mid":null,"last":0.03,"volume":10.0,"openInterest":0.0,"iv":0.500005,"delta":0.0084,"gamma":0.0099,"theta":-0.0006,"vega":0.0004,"rho":0.0,"greeksSource":"cboe","greeksMissingReason":null},{"symbol":"ABR260821C00020000","expiration":"2026-08-21","side":"call","strike":20.0,"bid":0.0,"ask":1.0,"mid":null,"last":0.07,"volume":2.0,"openInterest":80.0,"iv":3.3828140429687497,"delta":0.0057,"gamma":0.0066,"theta":-0.0005,"vega":0.0002,"rho":0.0,"greeksSource":"cboe","greeksMissingReason":null},{"symbol":"ABR260821C00023000","expiration":"2026-08-21","side":"call","strike":23.0,"bid":0.0,"ask":0.05,"mid":null,"last":0.05,"volume":1.0,"openInterest":108.0,"iv":2.031254921875,"delta":0.0041,"gamma":0.0046,"theta":-0.0004,"vega":0.0002,"rho":0.0,"greeksSource":"cboe","greeksMissingReason":null},{"symbol":"ABR260821C00025000","expiration":"2026-08-21","side":"call","strike":25.0,"bid":0.0,"ask":0.0,"mid":null,"last":0.05,"volume":2.0,"openInterest":54.0,"iv":0.500005,"delta":0.0033,"gamma":0.0038,"theta":-0.0003,"vega":0.0001,"rho":0.0,"greeksSource":"cboe","greeksMissingReason":null},{"symbol":"ABR260821C00030000","expiration":"2026-08-21","side":"call","strike":30.0,"bid":0.0,"ask":0.0,"mid":null,"last":0.01,"volume":1.0,"openInterest":0.0,"iv":0.500005,"delta":0.0021,"gamma":0.0024,"theta":-0.0002,"vega":0.0001,"rho":0.0,"greeksSource":"cboe","greeksMissingReason":null},{"symbol":"ABR260821P00003000","expiration":"2026-08-21","side":"put","strike":3.0,"bid":0.0,"ask":0.1,"mid":null,"last":0.07,"volume":3.0,"openInterest":2377.0,"iv":1.109379453125,"delta":-0.081,"gamma":0.0829,"theta":-0.0034,"vega":0.0023,"rho":-0.0005,"greeksSource":"cboe","greeksMissingReason":null},{"symbol":"ABR260821P00004000","expiration":"2026-08-21","side":"put","strike":4.0,"bid":0.0,"ask":0.15,"mid":null,"last":0.1,"volume":1.0,"openInterest":12.0,"iv":0.6601596484375001,"delta":-0.1906,"gamma":0.2514,"theta":-0.0038,"vega":0.0042,"rho":-0.0011,"greeksSource":"cboe","greeksMissingReason":null},{"symbol":"ABR260821P00005000","expiration":"2026-08-21","side":"put","strike":5.0,"bid":0.35,"ask":0.4,"mid":0.375,"last":0.44,"volume":3.0,"openInterest":6314.0,"iv":0.57617611328125,"delta":-0.5971,"gamma":0.5383,"theta":-0.0036,"vega":0.006,"rho":-0.0033,"greeksSource":"cboe","greeksMissingReason":null},{"symbol":"ABR260821P00006000","expiration":"2026-08-21","side":"put","strike":6.0,"bid":1.05,"ask":1.25,"mid":1.15,"last":1.25,"volume":12.0,"openInterest":1143.0,"iv":0.6992217578125001,"delta":-0.8474,"gamma":0.2438,"theta":-0.0028,"vega":0.0037,"rho":-0.0052,"greeksSource":"cboe","greeksMissingReason":null},{"symbol":"ABR260821P00007000","expiration":"2026-08-21","side":"put","strike":7.0,"bid":1.95,"ask":2.2,"mid":2.075,"last":2.15,"volume":1.0,"openInterest":1090.0,"iv":0.8085956640624999,"delta":-0.9154,"gamma":0.1284,"theta":-0.0022,"vega":0.0024,"rho":-0.0064,"greeksSource":"cboe","greeksMissingReason":null},{"symbol":"ABR260821P00008000","expiration":"2026-08-21","side":"put","strike":8.0,"bid":3.0,"ask":3.2,"mid":3.1,"last":3.2,"volume":4.0,"openInterest":6690.0,"iv":1.0976607617187502,"delta":-0.9449,"gamma":0.0799,"theta":-0.0017,"vega":0.0017,"rho":-0.0074,"greeksSource":"cboe","greeksMissingReason":null},{"symbol":"ABR260821P00009000","expiration":"2026-08-21","side":"put","strike":9.0,"bid":3.6,"ask":4.8,"mid":4.2,"last":4.2,"volume":4.0,"openInterest":354.0,"iv":1.54297103515625,"delta":-0.9609,"gamma":0.0548,"theta":-0.0013,"vega":0.0013,"rho":-0.0084,"greeksSource":"cboe","greeksMissingReason":null},{"symbol":"ABR260821P00010000","expiration":"2026-08-21","side":"put","strike":10.0,"bid":4.9,"ask":5.2,"mid":5.050000000000001,"last":5.1,"volume":17.0,"openInterest":1008.0,"iv":1.2343788281249999,"delta":-0.9708,"gamma":0.04,"theta":-0.0009,"vega":0.0011,"rho":-0.0094,"greeksSource":"cboe","greeksMissingReason":null},{"symbol":"ABR260821P00011000","expiration":"2026-08-21","side":"put","strike":11.0,"bid":5.6,"ask":6.8,"mid":6.199999999999999,"last":5.9,"volume":2.0,"openInterest":23.0,"iv":1.859375703125,"delta":-0.9774,"gamma":0.0306,"theta":-0.0006,"vega":0.0009,"rho":-0.0103,"greeksSource":"cboe","greeksMissingReason":null},{"symbol":"ABR260821P00012000","expiration":"2026-08-21","side":"put","strike":12.0,"bid":0.0,"ask":0.0,"mid":null,"last":6.3,"volume":1.0,"openInterest":0.0,"iv":1.0000000000000003e-05,"delta":-0.982,"gamma":0.0241,"theta":-0.0004,"vega":0.0007,"rho":-0.0112,"greeksSource":"cboe","greeksMissingReason":null},{"symbol":"ABR260821P00013000","expiration":"2026-08-21","side":"put","strike":13.0,"bid":8.0,"ask":8.2,"mid":8.1,"last":7.9,"volume":1.0,"openInterest":795.0,"iv":1.7968760156249999,"delta":-0.9854,"gamma":0.0194,"theta":-0.0002,"vega":0.0006,"rho":-0.0122,"greeksSource":"cboe","greeksMissingReason":null},{"symbol":"ABR260821P00015000","expiration":"2026-08-21","side":"put","strike":15.0,"bid":9.7,"ask":11.7,"mid":10.7,"last":10.0,"volume":1.0,"openInterest":121.0,"iv":3.3242204394531245,"delta":-0.99,"gamma":0.0134,"theta":0.0,"vega":0.0004,"rho":-0.014,"greeksSource":"cboe","greeksMissingReason":null},{"symbol":"ABR260821P00017000","expiration":"2026-08-21","side":"put","strike":17.0,"bid":0.0,"ask":0.0,"mid":null,"last":11.25,"volume":7.0,"openInterest":0.0,"iv":1.0000000000000003e-05,"delta":-0.9929,"gamma":0.0097,"theta":0.0,"vega":0.0003,"rho":-0.0159,"greeksSource":"cboe","greeksMissingReason":null},{"symbol":"ABR260821P00020000","expiration":"2026-08-21","side":"put","strike":20.0,"bid":9.0,"ask":11.5,"mid":10.25,"last":9.0,"volume":3.0,"openInterest":5.0,"iv":1.0000000000000003e-05,"delta":-0.9956,"gamma":0.0065,"theta":0.0,"vega":0.0002,"rho":-0.0187,"greeksSource":"cboe","greeksMissingReason":null},{"symbol":"ABR260821P00023000","expiration":"2026-08-21","side":"put","strike":23.0,"bid":8.0,"ask":11.6,"mid":9.8,"last":9.8,"volume":17.0,"openInterest":93.0,"iv":1.0000000000000003e-05,"delta":-0.9972,"gamma":0.0046,"theta":0.0,"vega":0.0002,"rho":-0.0215,"greeksSource":"cboe","greeksMissingReason":null},{"symbol":"ABR260821P00025000","expiration":"2026-08-21","side":"put","strike":25.0,"bid":20.0,"ask":20.2,"mid":20.1,"last":19.9,"volume":2.0,"openInterest":119.0,"iv":2.60156599609375,"delta":-0.9979,"gamma":0.0037,"theta":0.0,"vega":0.0001,"rho":-0.0233,"greeksSource":"cboe","greeksMissingReason":null},{"symbol":"ABR260821P00030000","expiration":"2026-08-21","side":"put","strike":30.0,"bid":23.9,"ask":27.2,"mid":25.549999999999997,"last":24.9,"volume":2.0,"openInterest":0.0,"iv":4.019536225585938,"delta":-0.9991,"gamma":0.0023,"theta":0.0,"vega":0.0001,"rho":-0.028,"greeksSource":"cboe","greeksMissingReason":null},{"symbol":"ABR260828C00001000","expiration":"2026-08-28","side":"call","strike":1.0,"bid":null,"ask":null,"mid":null,"last":4.1,"volume":null,"openInterest":null,"iv":0.0,"delta":0.992,"gamma":0.0058,"theta":-0.0008,"vega":0.0004,"rho":0.0008,"greeksSource":"cboe","greeksMissingReason":null},{"symbol":"ABR260828C00005000","expiration":"2026-08-28","side":"call","strike":5.0,"bid":0.25,"ask":0.45,"mid":0.35,"last":0.31,"volume":1.0,"openInterest":20.0,"iv":0.6367223828125,"delta":0.4868,"gamma":0.5551,"theta":-0.0038,"vega":0.0064,"rho":0.0021,"greeksSource":"cboe","greeksMissingReason":null},{"symbol":"ABR260828C00006000","expiration":"2026-08-28","side":"call","strike":6.0,"bid":0.0,"ask":0.1,"mid":null,"last":0.08,"volume":1.0,"openInterest":2.0,"iv":0.5468795312500001,"delta":0.1854,"gamma":0.2686,"theta":-0.0031,"vega":0.0045,"rho":0.0009,"greeksSource":"cboe","greeksMissingReason":null},{"symbol":"ABR261016C00001000","expiration":"2026-10-16","side":"call","strike":1.0,"bid":2.75,"ask":5.3,"mid":4.025,"last":4.09,"volume":2.0,"openInterest":0.0,"iv":1.734376328125,"delta":0.9981,"gamma":0.0037,"theta":0.0,"vega":0.0002,"rho":0.0009,"greeksSource":"cboe","greeksMissingReason":null},{"symbol":"ABR261016C00002000","expiration":"2026-10-16","side":"call","strike":2.0,"bid":2.35,"ask":4.2,"mid":3.2750000000000004,"last":3.4,"volume":6.0,"openInterest":2.0,"iv":1.9296878515625,"delta":0.9813,"gamma":0.0228,"theta":-0.0006,"vega":0.001,"rho":0.0019,"greeksSource":"cboe","greeksMissingReason":null},{"symbol":"ABR261016C00003000","expiration":"2026-10-16","side":"call","strike":3.0,"bid":1.65,"ask":2.25,"mid":1.95,"last":2.3,"volume":2.0,"openInterest":1.0,"iv":1.1796916015624999,"delta":0.9358,"gamma":0.0792,"theta":-0.0016,"vega":0.0028,"rho":0.0032,"greeksSource":"cboe","greeksMissingReason":null},{"symbol":"ABR261016C00004000","expiration":"2026-10-16","side":"call","strike":4.0,"bid":0.65,"ask":1.4,"mid":1.025,"last":1.38,"volume":1.0,"openInterest":15.0,"iv":0.8867198828124999,"delta":0.8081,"gamma":0.2213,"theta":-0.0025,"vega":0.0065,"rho":0.005,"greeksSource":"cboe","greeksMissingReason":null},{"symbol":"ABR261016C00005000","expiration":"2026-10-16","side":"call","strike":5.0,"bid":0.35,"ask":0.5,"mid":0.425,"last":0.37,"volume":10.0,"openInterest":149.0,"iv":0.49219257812500006,"delta":0.4982,"gamma":0.3743,"theta":-0.0024,"vega":0.0096,"rho":0.0049,"greeksSource":"cboe","greeksMissingReason":null},{"symbol":"ABR261016C00006000","expiration":"2026-10-16","side":"call","strike":6.0,"bid":0.1,"ask":0.2,"mid":0.15000000000000002,"last":0.1,"volume":19.0,"openInterest":962.0,"iv":0.507817421875,"delta":0.2127,"gamma":0.2599,"theta":-0.0017,"vega":0.0071,"rho":0.0024,"greeksSource":"cboe","greeksMissingReason":null},{"symbol":"ABR261016C00007000","expiration":"2026-10-16","side":"call","strike":7.0,"bid":0.0,"ask":0.15,"mid":null,"last":0.02,"volume":628.0,"openInterest":764.0,"iv":0.5195360546875,"delta":0.1016,"gamma":0.1418,"theta":-0.0011,"vega":0.0043,"rho":0.0011,"greeksSource":"cboe","greeksMissingReason":null},{"symbol":"ABR261016C00008000","expiration":"2026-10-16","side":"call","strike":8.0,"bid":0.0,"ask":0.1,"mid":null,"last":0.05,"volume":1.0,"openInterest":180.0,"iv":0.5937540625000001,"delta":0.0571,"gamma":0.0825,"theta":-0.0008,"vega":0.0028,"rho":0.0006,"greeksSource":"cboe","greeksMissingReason":null},{"symbol":"ABR261016C00009000","expiration":"2026-10-16","side":"call","strike":9.0,"bid":0.0,"ask":0.05,"mid":null,"last":0.02,"volume":43.0,"openInterest":405.0,"iv":0.6171913281250001,"delta":0.0357,"gamma":0.052,"theta":-0.0006,"vega":0.0019,"rho":0.0004,"greeksSource":"cboe","greeksMissingReason":null},{"symbol":"ABR261016C00010000","expiration":"2026-10-16","side":"call","strike":10.0,"bid":0.0,"ask":0.25,"mid":null,"last":0.01,"volume":3.0,"openInterest":385.0,"iv":0.9687503125,"delta":0.024,"gamma":0.0349,"theta":-0.0004,"vega":0.0014,"rho":0.0003,"greeksSource":"cboe","greeksMissingReason":null},{"symbol":"ABR261016C00011000","expiration":"2026-10-16","side":"call","strike":11.0,"bid":0.0,"ask":0.2,"mid":null,"last":0.03,"volume":4.0,"openInterest":6.0,"iv":1.0039112304687499,"delta":0.017,"gamma":0.0246,"theta":-0.0004,"vega":0.001,"rho":0.0002,"greeksSource":"cboe","greeksMissingReason":null},{"symbol":"ABR261016C00012000","expiration":"2026-10-16","side":"call","strike":12.0,"bid":0.0,"ask":0.1,"mid":null,"last":0.05,"volume":2.0,"openInterest":10.0,"iv":0.945313046875,"delta":0.0125,"gamma":0.0181,"theta":-0.0003,"vega":0.0008,"rho":0.0001,"greeksSource":"cboe","greeksMissingReason":null},{"symbol":"ABR261016C00014000","expiration":"2026-10-16","side":"call","strike":14.0,"bid":null,"ask":0.75,"mid":null,"last":0.07,"volume":null,"openInterest":1.0,"iv":2.1152390869140625,"delta":0.0074,"gamma":0.0105,"theta":-0.0002,"vega":0.0005,"rho":0.0001,"greeksSource":"cboe","greeksMissingReason":null},{"symbol":"ABR261016P00003000","expiration":"2026-10-16","side":"put","strike":3.0,"bid":0.0,"ask":0.0,"mid":null,"last":0.46,"volume":null,"openInterest":0.0,"iv":0.2500075,"delta":-0.1027,"gamma":0.0838,"theta":-0.002,"vega":0.0043,"rho":-0.0015,"greeksSource":"cboe","greeksMissingReason":null},{"symbol":"ABR261016P00004000","expiration":"2026-10-16","side":"put","strike":4.0,"bid":0.1,"ask":0.2,"mid":0.15000000000000002,"last":0.15,"volume":47.0,"openInterest":987.0,"iv":0.5468795312500001,"delta":-0.2316,"gamma":0.2049,"theta":-0.0024,"vega":0.0074,"rho":-0.0031,"greeksSource":"cboe","greeksMissingReason":null},{"symbol":"ABR261016P00005000","expiration":"2026-10-16","side":"put","strike":5.0,"bid":0.5,"ask":0.6,"mid":0.55,"last":0.55,"volume":10.0,"openInterest":470.0,"iv":0.5429733203125001,"delta":-0.5283,"gamma":0.3697,"theta":-0.0024,"vega":0.0096,"rho":-0.006,"greeksSource":"cboe","greeksMissingReason":null},{"symbol":"ABR261016P00006000","expiration":"2026-10-16","side":"put","strike":6.0,"bid":1.0,"ask":1.45,"mid":1.225,"last":1.36,"volume":4.0,"openInterest":19426.0,"iv":0.5351608984375,"delta":-0.8186,"gamma":0.2668,"theta":-0.0016,"vega":0.0063,"rho":-0.0076,"greeksSource":"cboe","greeksMissingReason":null},{"symbol":"ABR261016P00007000","expiration":"2026-10-16","side":"put","strike":7.0,"bid":1.85,"ask":2.3,"mid":2.075,"last":2.12,"volume":2.0,"openInterest":793.0,"iv":0.5195360546875,"delta":-0.927,"gamma":0.1342,"theta":-0.0007,"vega":0.0034,"rho":-0.008,"greeksSource":"cboe","greeksMissingReason":null},{"symbol":"ABR261016P00008000","expiration":"2026-10-16","side":"put","strike":8.0,"bid":3.0,"ask":3.8,"mid":3.4,"last":3.19,"volume":2.0,"openInterest":1542.0,"iv":1.111332568359375,"delta":-0.966,"gamma":0.07,"theta":-0.0002,"vega":0.0018,"rho":-0.0084,"greeksSource":"cboe","greeksMissingReason":null},{"symbol":"ABR261016P00009000","expiration":"2026-10-16","side":"put","strike":9.0,"bid":3.2,"ask":4.8,"mid":4.0,"last":4.2,"volume":4.0,"openInterest":778.0,"iv":1.681642216796875,"delta":-0.9826,"gamma":0.0394,"theta":0.0,"vega":0.0011,"rho":-0.0091,"greeksSource":"cboe","greeksMissingReason":null},{"symbol":"ABR261016P00010000","expiration":"2026-10-16","side":"put","strike":10.0,"bid":0.0,"ask":0.0,"mid":null,"last":4.7,"volume":1.0,"openInterest":0.0,"iv":1.0000000000000003e-05,"delta":-0.9908,"gamma":0.0237,"theta":0.0,"vega":0.0007,"rho":-0.0098,"greeksSource":"cboe","greeksMissingReason":null},{"symbol":"ABR261016P00011000","expiration":"2026-10-16","side":"put","strike":11.0,"bid":0.0,"ask":0.0,"mid":null,"last":5.36,"volume":1.0,"openInterest":0.0,"iv":1.0000000000000003e-05,"delta":-0.9951,"gamma":0.0149,"theta":0.0,"vega":0.0004,"rho":-0.0106,"greeksSource":"cboe","greeksMissingReason":null},{"symbol":"ABR261016P00012000","expiration":"2026-10-16","side":"put","strike":12.0,"bid":0.0,"ask":0.0,"mid":null,"last":4.75,"volume":3.0,"openInterest":0.0,"iv":1.0000000000000003e-05,"delta":-0.9977,"gamma":0.0098,"theta":0.0,"vega":0.0003,"rho":-0.0114,"greeksSource":"cboe","greeksMissingReason":null},{"symbol":"ABR261016P00013000","expiration":"2026-10-16","side":"put","strike":13.0,"bid":0.0,"ask":0.0,"mid":null,"last":7.45,"volume":5.0,"openInterest":0.0,"iv":1.0000000000000003e-05,"delta":-0.9992,"gamma":0.0066,"theta":0.0,"vega":0.0002,"rho":-0.0123,"greeksSource":"cboe","greeksMissingReason":null},{"symbol":"ABR261016P00014000","expiration":"2026-10-16","side":"put","strike":14.0,"bid":6.8,"ask":10.7,"mid":8.75,"last":6.37,"volume":1.0,"openInterest":2.0,"iv":3.0683617041015623,"delta":-1.0,"gamma":0.0046,"theta":0.0,"vega":0.0001,"rho":-0.0132,"greeksSource":"cboe","greeksMissingReason":null},{"symbol":"ABR270115C00001000","expiration":"2027-01-15","side":"call","strike":1.0,"bid":2.7,"ask":6.0,"mid":4.35,"last":4.15,"volume":4.0,"openInterest":1.0,"iv":2.6250034375,"delta":1.0,"gamma":0.0,"theta":0.0,"vega":0.0,"rho":0.0008,"greeksSource":"cboe","greeksMissingReason":null},{"symbol":"ABR270115C00002000","expiration":"2027-01-15","side":"call","strike":2.0,"bid":2.55,"ask":4.2,"mid":3.375,"last":3.08,"volume":2.0,"openInterest":4.0,"iv":1.5664084179687499,"delta":0.9979,"gamma":0.0066,"theta":0.0,"vega":0.0002,"rho":0.0018,"greeksSource":"cboe","greeksMissingReason":null},{"symbol":"ABR270115C00003000","expiration":"2027-01-15","side":"call","strike":3.0,"bid":1.6,"ask":3.6,"mid":2.6,"last":2.14,"volume":2.0,"openInterest":17.0,"iv":1.2753942480468747,"delta":0.9526,"gamma":0.0794,"theta":-0.0008,"vega":0.003,"rho":0.0036,"greeksSource":"cboe","greeksMissingReason":null},{"symbol":"ABR270115C00004000","expiration":"2027-01-15","side":"call","strike":4.0,"bid":0.7,"ask":1.4,"mid":1.0499999999999998,"last":1.08,"volume":1.0,"openInterest":185.0,"iv":0.6347692773437501,"delta":0.7829,"gamma":0.221,"theta":-0.0017,"vega":0.0095,"rho":0.0086,"greeksSource":"cboe","greeksMissingReason":null},{"symbol":"ABR270115C00005000","expiration":"2027-01-15","side":"call","strike":5.0,"bid":0.45,"ask":0.65,"mid":0.55,"last":0.51,"volume":5.0,"openInterest":584.0,"iv":0.45898978515625005,"delta":0.5131,"gamma":0.2781,"theta":-0.0017,"vega":0.0129,"rho":0.0084,"greeksSource":"cboe","greeksMissingReason":null},{"symbol":"ABR270115C00006000","expiration":"2027-01-15","side":"call","strike":6.0,"bid":0.2,"ask":0.3,"mid":0.25,"last":0.25,"volume":48.0,"openInterest":3642.0,"iv":0.4414118359375,"delta":0.297,"gamma":0.229,"theta":-0.0014,"vega":0.0113,"rho":0.0056,"greeksSource":"cboe","greeksMissingReason":null},{"symbol":"ABR270115C00007000","expiration":"2027-01-15","side":"call","strike":7.0,"bid":0.05,"ask":0.2,"mid":0.125,"last":0.14,"volume":3.0,"openInterest":447.0,"iv":0.50586431640625,"delta":0.185,"gamma":0.1609,"theta":-0.0012,"vega":0.0088,"rho":0.0037,"greeksSource":"cboe","greeksMissingReason":null},{"symbol":"ABR270115C00008000","expiration":"2027-01-15","side":"call","strike":8.0,"bid":0.05,"ask":0.1,"mid":0.07500000000000001,"last":0.1,"volume":7.0,"openInterest":2239.0,"iv":0.5019581054687501,"delta":0.1281,"gamma":0.1157,"theta":-0.001,"vega":0.0069,"rho":0.0026,"greeksSource":"cboe","greeksMissingReason":null},{"symbol":"ABR270115C00009000","expiration":"2027-01-15","side":"call","strike":9.0,"bid":0.0,"ask":0.1,"mid":null,"last":0.09,"volume":30.0,"openInterest":188.0,"iv":0.500005,"delta":0.0959,"gamma":0.0873,"theta":-0.0009,"vega":0.0056,"rho":0.0019,"greeksSource":"cboe","greeksMissingReason":null},{"symbol":"ABR270115C00010000","expiration":"2027-01-15","side":"call","strike":10.0,"bid":0.05,"ask":0.1,"mid":0.07500000000000001,"last":0.1,"volume":3.0,"openInterest":3323.0,"iv":0.6171913281250001,"delta":0.0757,"gamma":0.0687,"theta":-0.0008,"vega":0.0047,"rho":0.0015,"greeksSource":"cboe","greeksMissingReason":null},{"symbol":"ABR270115C00011000","expiration":"2027-01-15","side":"call","strike":11.0,"bid":0.0,"ask":0.0,"mid":null,"last":0.15,"volume":3.0,"openInterest":0.0,"iv":0.2500075,"delta":0.0622,"gamma":0.0559,"theta":-0.0007,"vega":0.004,"rho":0.0012,"greeksSource":"cboe","greeksMissingReason":null},{"symbol":"ABR270115C00012000","expiration":"2027-01-15","side":"call","strike":12.0,"bid":0.0,"ask":0.05,"mid":null,"last":0.03,"volume":7.0,"openInterest":1841.0,"iv":0.6015664843750002,"delta":0.0525,"gamma":0.0467,"theta":-0.0006,"vega":0.0035,"rho":0.001,"greeksSource":"cboe","greeksMissingReason":null},{"symbol":"ABR270115C00015000","expiration":"2027-01-15","side":"call","strike":15.0,"bid":0.0,"ask":0.0,"mid":null,"last":0.05,"volume":29.0,"openInterest":0.0,"iv":0.500005,"delta":0.0355,"gamma":0.0306,"theta":-0.0005,"vega":0.0026,"rho":0.0007,"greeksSource":"cboe","greeksMissingReason":null},{"symbol":"ABR270115C00017000","expiration":"2027-01-15","side":"call","strike":17.0,"bid":0.0,"ask":0.05,"mid":null,"last":0.05,"volume":57.0,"openInterest":2079.0,"iv":0.7812521875,"delta":0.0292,"gamma":0.0246,"theta":-0.0004,"vega":0.0022,"rho":0.0006,"greeksSource":"cboe","greeksMissingReason":null},{"symbol":"ABR270115C00020000","expiration":"2027-01-15","side":"call","strike":20.0,"bid":0.0,"ask":0.1,"mid":null,"last":0.05,"volume":15.0,"openInterest":157.0,"iv":0.9531254687499999,"delta":0.023,"gamma":0.0188,"theta":-0.0004,"vega":0.0018,"rho":0.0004,"greeksSource":"cboe","greeksMissingReason":null},{"symbol":"ABR270115C00022000","expiration":"2027-01-15","side":"call","strike":22.0,"bid":0.0,"ask":0.15,"mid":null,"last":0.75,"volume":2.0,"openInterest":58.0,"iv":1.0703171484375003,"delta":0.0201,"gamma":0.0162,"theta":-0.0004,"vega":0.0016,"rho":0.0004,"greeksSource":"cboe","greeksMissingReason":null},{"symbol":"ABR270115C00025000","expiration":"2027-01-15","side":"call","strike":25.0,"bid":0.0,"ask":3.4,"mid":null,"last":0.07,"volume":50.0,"openInterest":53.0,"iv":2.5898472753906248,"delta":0.017,"gamma":0.0134,"theta":-0.0003,"vega":0.0014,"rho":0.0003,"greeksSource":"cboe","greeksMissingReason":null},{"symbol":"ABR270115C00030000","expiration":"2027-01-15","side":"call","strike":30.0,"bid":0.0,"ask":0.0,"mid":null,"last":0.06,"volume":4.0,"openInterest":0.0,"iv":0.500005,"delta":0.0136,"gamma":0.0104,"theta":-0.0003,"vega":0.0011,"rho":0.0003,"greeksSource":"cboe","greeksMissingReason":null},{"symbol":"ABR270115P00003000","expiration":"2027-01-15","side":"put","strike":3.0,"bid":0.05,"ask":0.2,"mid":0.125,"last":0.15,"volume":1.0,"openInterest":2794.0,"iv":0.6562534375000001,"delta":-0.1223,"gamma":0.0927,"theta":-0.0012,"vega":0.0066,"rho":-0.0035,"greeksSource":"cboe","greeksMissingReason":null},{"symbol":"ABR270115P00004000","expiration":"2027-01-15","side":"put","strike":4.0,"bid":0.25,"ask":0.4,"mid":0.325,"last":0.37,"volume":6.0,"openInterest":94.0,"iv":0.5664105859375,"delta":-0.275,"gamma":0.1941,"theta":-0.0015,"vega":0.0109,"rho":-0.0074,"greeksSource":"cboe","greeksMissingReason":null},{"symbol":"ABR270115P00005000","expiration":"2027-01-15","side":"put","strike":5.0,"bid":0.7,"ask":0.85,"mid":0.7749999999999999,"last":0.85,"volume":14.0,"openInterest":23599.0,"iv":0.5478560839843751,"delta":-0.5197,"gamma":0.2694,"theta":-0.0016,"vega":0.013,"rho":-0.0135,"greeksSource":"cboe","greeksMissingReason":null},{"symbol":"ABR270115P00006000","expiration":"2027-01-15","side":"put","strike":6.0,"bid":1.25,"ask":1.9,"mid":1.575,"last":1.55,"volume":2.0,"openInterest":4478.0,"iv":0.6435582519531251,"delta":-0.7266,"gamma":0.225,"theta":-0.0012,"vega":0.0109,"rho":-0.0193,"greeksSource":"cboe","greeksMissingReason":null},{"symbol":"ABR270115P00007000","expiration":"2027-01-15","side":"put","strike":7.0,"bid":2.05,"ask":2.8,"mid":2.425,"last":2.35,"volume":1.0,"openInterest":1122.0,"iv":0.69336244140625,"delta":-0.8342,"gamma":0.1575,"theta":-0.0009,"vega":0.0082,"rho":-0.0238,"greeksSource":"cboe","greeksMissingReason":null},{"symbol":"ABR270115P00008000","expiration":"2027-01-15","side":"put","strike":8.0,"bid":3.1,"ask":3.8,"mid":3.45,"last":3.3,"volume":3.0,"openInterest":3122.0,"iv":0.8349625878906248,"delta":-0.8886,"gamma":0.1119,"theta":-0.0006,"vega":0.0063,"rho":-0.0278,"greeksSource":"cboe","greeksMissingReason":null},{"symbol":"ABR270115P00009000","expiration":"2027-01-15","side":"put","strike":9.0,"bid":0.0,"ask":0.0,"mid":null,"last":3.55,"volume":2.0,"openInterest":0.0,"iv":1.0000000000000003e-05,"delta":-0.9191,"gamma":0.0833,"theta":-0.0003,"vega":0.005,"rho":-0.0313,"greeksSource":"cboe","greeksMissingReason":null},{"symbol":"ABR270115P00010000","expiration":"2027-01-15","side":"put","strike":10.0,"bid":4.8,"ask":5.6,"mid":5.199999999999999,"last":5.2,"volume":1.0,"openInterest":1349.0,"iv":0.7851583984375,"delta":-0.9378,"gamma":0.0647,"theta":-0.0001,"vega":0.0042,"rho":-0.0348,"greeksSource":"cboe","greeksMissingReason":null},{"symbol":"ABR270115P00011000","expiration":"2027-01-15","side":"put","strike":11.0,"bid":5.5,"ask":7.0,"mid":6.25,"last":5.6,"volume":1.0,"openInterest":34.0,"iv":0.9062509375,"delta":-0.9503,"gamma":0.0521,"theta":0.0,"vega":0.0035,"rho":-0.0382,"greeksSource":"cboe","greeksMissingReason":null},{"symbol":"ABR270115P00012000","expiration":"2027-01-15","side":"put","strike":12.0,"bid":7.0,"ask":7.3,"mid":7.15,"last":6.82,"volume":4.0,"openInterest":338.0,"iv":0.8476577734374999,"delta":-0.9591,"gamma":0.0431,"theta":0.0,"vega":0.003,"rho":-0.0417,"greeksSource":"cboe","greeksMissingReason":null},{"symbol":"ABR270115P00013000","expiration":"2027-01-15","side":"put","strike":13.0,"bid":8.0,"ask":8.3,"mid":8.15,"last":8.0,"volume":151.0,"openInterest":176.0,"iv":0.9003916210937499,"delta":-0.9656,"gamma":0.0365,"theta":0.0,"vega":0.0027,"rho":-0.0451,"greeksSource":"cboe","greeksMissingReason":null},{"symbol":"ABR270115P00015000","expiration":"2027-01-15","side":"put","strike":15.0,"bid":10.0,"ask":10.3,"mid":10.15,"last":9.71,"volume":10.0,"openInterest":5153.0,"iv":0.9882813671875,"delta":-0.9778,"gamma":0.0277,"theta":0.0,"vega":0.0017,"rho":-0.0247,"greeksSource":"cboe","greeksMissingReason":null},{"symbol":"ABR270115P00017000","expiration":"2027-01-15","side":"put","strike":17.0,"bid":10.5,"ask":13.0,"mid":11.75,"last":9.79,"volume":2.0,"openInterest":59.0,"iv":1.8369148779296873,"delta":-0.9878,"gamma":0.0188,"theta":0.0,"vega":0.0011,"rho":-0.0206,"greeksSource":"cboe","greeksMissingReason":null},{"symbol":"ABR270115P00020000","expiration":"2027-01-15","side":"put","strike":20.0,"bid":14.1,"ask":16.1,"mid":15.100000000000001,"last":14.16,"volume":5.0,"openInterest":56.0,"iv":1.0742233789062503,"delta":-0.9945,"gamma":0.0103,"theta":0.0,"vega":0.0006,"rho":-0.0202,"greeksSource":"cboe","greeksMissingReason":null},{"symbol":"ABR270115P00025000","expiration":"2027-01-15","side":"put","strike":25.0,"bid":13.2,"ask":17.35,"mid":15.275,"last":16.53,"volume":null,"openInterest":1.0,"iv":1.0000000000000003e-05,"delta":-0.9983,"gamma":0.0045,"theta":0.0,"vega":0.0002,"rho":-0.0237,"greeksSource":"cboe","greeksMissingReason":null},{"symbol":"ABR270115P00030000","expiration":"2027-01-15","side":"put","strike":30.0,"bid":23.3,"ask":27.0,"mid":25.15,"last":23.37,"volume":1.0,"openInterest":34.0,"iv":1.3828155859374998,"delta":-0.9997,"gamma":0.0024,"theta":0.0,"vega":0.0001,"rho":-0.0282,"greeksSource":"cboe","greeksMissingReason":null},{"symbol":"ABR280121C00003000","expiration":"2028-01-21","side":"call","strike":3.0,"bid":1.85,"ask":2.75,"mid":2.3,"last":1.99,"volume":35.0,"openInterest":106.0,"iv":0.52539537109375,"delta":0.959,"gamma":0.0824,"theta":-0.0004,"vega":0.0032,"rho":0.0057,"greeksSource":"cboe","greeksMissingReason":null},{"symbol":"ABR280121C00005000","expiration":"2028-01-21","side":"call","strike":5.0,"bid":0.8,"ask":0.95,"mid":0.875,"last":0.85,"volume":150.0,"openInterest":3113.0,"iv":0.3891662646484375,"delta":0.5562,"gamma":0.1814,"theta":-0.0008,"vega":0.0191,"rho":0.0205,"greeksSource":"cboe","greeksMissingReason":null},{"symbol":"ABR280121C00008000","expiration":"2028-01-21","side":"call","strike":8.0,"bid":0.25,"ask":0.35,"mid":0.3,"last":0.27,"volume":4.0,"openInterest":2746.0,"iv":0.43457596679687505,"delta":0.2455,"gamma":0.1317,"theta":-0.0006,"vega":0.0155,"rho":0.0119,"greeksSource":"cboe","greeksMissingReason":null},{"symbol":"ABR280121C00010000","expiration":"2028-01-21","side":"call","strike":10.0,"bid":0.0,"ask":0.4,"mid":null,"last":0.17,"volume":1.0,"openInterest":1153.0,"iv":0.5644574804687501,"delta":0.1662,"gamma":0.0983,"theta":-0.0005,"vega":0.0122,"rho":0.0083,"greeksSource":"cboe","greeksMissingReason":null},{"symbol":"ABR280121C00012000","expiration":"2028-01-21","side":"call","strike":12.0,"bid":0.05,"ask":0.2,"mid":0.125,"last":0.06,"volume":1.0,"openInterest":463.0,"iv":0.526371923828125,"delta":0.1233,"gamma":0.0761,"theta":-0.0005,"vega":0.01,"rho":0.0062,"greeksSource":"cboe","greeksMissingReason":null},{"symbol":"ABR280121C00015000","expiration":"2028-01-21","side":"call","strike":15.0,"bid":0.05,"ask":0.2,"mid":0.125,"last":0.07,"volume":11.0,"openInterest":511.0,"iv":0.5488326367187502,"delta":0.0879,"gamma":0.0558,"theta":-0.0004,"vega":0.0078,"rho":0.0045,"greeksSource":"cboe","greeksMissingReason":null},{"symbol":"ABR280121C00017000","expiration":"2028-01-21","side":"call","strike":17.0,"bid":0.0,"ask":0.0,"mid":null,"last":0.01,"volume":3.0,"openInterest":0.0,"iv":0.2500075,"delta":0.0735,"gamma":0.047,"theta":-0.0004,"vega":0.0068,"rho":0.0037,"greeksSource":"cboe","greeksMissingReason":null},{"symbol":"ABR280121C00020000","expiration":"2028-01-21","side":"call","strike":20.0,"bid":0.0,"ask":0.75,"mid":null,"last":0.05,"volume":1.0,"openInterest":7.0,"iv":0.8261736132812498,"delta":0.0589,"gamma":0.0379,"theta":-0.0003,"vega":0.0057,"rho":0.003,"greeksSource":"cboe","greeksMissingReason":null},{"symbol":"ABR280121C00022000","expiration":"2028-01-21","side":"call","strike":22.0,"bid":null,"ask":0.15,"mid":null,"last":0.05,"volume":null,"openInterest":1.0,"iv":0.70117486328125,"delta":0.052,"gamma":0.0335,"theta":-0.0003,"vega":0.0052,"rho":0.0026,"greeksSource":"cboe","greeksMissingReason":null},{"symbol":"ABR280121P00003000","expiration":"2028-01-21","side":"put","strike":3.0,"bid":0.4,"ask":0.55,"mid":0.47500000000000003,"last":0.47,"volume":3.0,"openInterest":1191.0,"iv":0.6513706738281251,"delta":-0.2019,"gamma":0.0973,"theta":-0.0007,"vega":0.0138,"rho":-0.0196,"greeksSource":"cboe","greeksMissingReason":null},{"symbol":"ABR280121P00005000","expiration":"2028-01-21","side":"put","strike":5.0,"bid":1.25,"ask":1.6,"mid":1.425,"last":1.5,"volume":2.0,"openInterest":1244.0,"iv":0.5918009570312501,"delta":-0.4926,"gamma":0.1707,"theta":-0.0007,"vega":0.0196,"rho":-0.0498,"greeksSource":"cboe","greeksMissingReason":null},{"symbol":"ABR280121P00008000","expiration":"2028-01-21","side":"put","strike":8.0,"bid":2.65,"ask":5.0,"mid":3.825,"last":3.6,"volume":1000.0,"openInterest":8947.0,"iv":0.6440465283203125,"delta":-0.7796,"gamma":0.1293,"theta":-0.0002,"vega":0.015,"rho":-0.0984,"greeksSource":"cboe","greeksMissingReason":null},{"symbol":"ABR280121P00010000","expiration":"2028-01-21","side":"put","strike":10.0,"bid":4.7,"ask":5.9,"mid":5.300000000000001,"last":5.5,"volume":400.0,"openInterest":1725.0,"iv":0.5127001855468749,"delta":-0.8563,"gamma":0.0961,"theta":0.0,"vega":0.0117,"rho":-0.1269,"greeksSource":"cboe","greeksMissingReason":null},{"symbol":"ABR280121P00012000","expiration":"2028-01-21","side":"put","strike":12.0,"bid":6.7,"ask":7.7,"mid":7.2,"last":7.29,"volume":3.0,"openInterest":282.0,"iv":0.5273484765625001,"delta":-0.8977,"gamma":0.074,"theta":0.0,"vega":0.0095,"rho":-0.1539,"greeksSource":"cboe","greeksMissingReason":null},{"symbol":"ABR280121P00015000","expiration":"2028-01-21","side":"put","strike":15.0,"bid":0.0,"ask":0.0,"mid":null,"last":9.5,"volume":2.0,"openInterest":0.0,"iv":1.0000000000000003e-05,"delta":-0.948,"gamma":0.0582,"theta":0.0,"vega":0.0051,"rho":-0.0589,"greeksSource":"cboe","greeksMissingReason":null},{"symbol":"ABR280121P00017000","expiration":"2028-01-21","side":"put","strike":17.0,"bid":10.5,"ask":13.1,"mid":11.8,"last":10.43,"volume":2.0,"openInterest":33.0,"iv":1.1044966650390626,"delta":-0.9816,"gamma":0.0357,"theta":0.0,"vega":0.0015,"rho":-0.0261,"greeksSource":"cboe","greeksMissingReason":null},{"symbol":"ABR280121P00020000","expiration":"2028-01-21","side":"put","strike":20.0,"bid":0.0,"ask":0.0,"mid":null,"last":13.6,"volume":14.0,"openInterest":0.0,"iv":1.0000000000000003e-05,"delta":-0.9976,"gamma":0.0092,"theta":0.0,"vega":0.0004,"rho":-0.021,"greeksSource":"cboe","greeksMissingReason":null},{"symbol":"ABR280121P00022000","expiration":"2028-01-21","side":"put","strike":22.0,"bid":0.0,"ask":0.0,"mid":null,"last":15.28,"volume":null,"openInterest":0.0,"iv":1.0000000000000003e-05,"delta":-1.0,"gamma":0.0035,"theta":0.0,"vega":0.0,"rho":-0.0219,"greeksSource":"cboe","greeksMissingReason":null}]}