{"symbol":"DUSL","updated":"2026-07-14T18:15:30.669153-04:00","underlyingPrice":95.83000183105469,"greeks":{"enabled":true,"primarySource":"cboe","fallbackSource":"client-black-scholes","riskFreeRate":null,"dividendYield":null,"total":48,"cboeMatched":48,"computed":0,"missing":0,"cboeContracts":234},"expirations":["2026-07-17","2026-08-21","2026-09-18","2026-12-18"],"quotes":[{"symbol":"DUSL260717C00082000","expiration":"2026-07-17","side":"call","strike":82.0,"bid":0.0,"ask":0.0,"mid":null,"last":11.52,"volume":1.0,"openInterest":0.0,"iv":1.0000000000000003e-05,"delta":0.8844,"gamma":0.0143,"theta":-0.421,"vega":0.0171,"rho":0.0096,"greeksSource":"cboe","greeksMissingReason":null},{"symbol":"DUSL260717C00083000","expiration":"2026-07-17","side":"call","strike":83.0,"bid":11.7,"ask":16.8,"mid":14.25,"last":14.25,"volume":4.0,"openInterest":1.0,"iv":1.5224633251953121,"delta":0.875,"gamma":0.0156,"theta":-0.4327,"vega":0.0181,"rho":0.0096,"greeksSource":"cboe","greeksMissingReason":null},{"symbol":"DUSL260717C00085000","expiration":"2026-07-17","side":"call","strike":85.0,"bid":0.0,"ask":0.0,"mid":null,"last":8.79,"volume":null,"openInterest":0.0,"iv":1.0000000000000003e-05,"delta":0.8528,"gamma":0.019,"theta":-0.4561,"vega":0.0202,"rho":0.0096,"greeksSource":"cboe","greeksMissingReason":null},{"symbol":"DUSL260717C00089000","expiration":"2026-07-17","side":"call","strike":89.0,"bid":6.1,"ask":11.2,"mid":8.649999999999999,"last":10.16,"volume":1.0,"openInterest":0.0,"iv":1.1464886425781249,"delta":0.7884,"gamma":0.0287,"theta":-0.4985,"vega":0.0254,"rho":0.0092,"greeksSource":"cboe","greeksMissingReason":null},{"symbol":"DUSL260717C00090000","expiration":"2026-07-17","side":"call","strike":90.0,"bid":5.3,"ask":10.5,"mid":7.9,"last":7.06,"volume":6.0,"openInterest":7.0,"iv":1.1303754418945315,"delta":0.7662,"gamma":0.032,"theta":-0.5068,"vega":0.0269,"rho":0.0091,"greeksSource":"cboe","greeksMissingReason":null},{"symbol":"DUSL260717C00094000","expiration":"2026-07-17","side":"call","strike":94.0,"bid":1.95,"ask":7.4,"mid":4.675,"last":12.0,"volume":null,"openInterest":50.0,"iv":0.930664755859375,"delta":0.6344,"gamma":0.0495,"theta":-0.5135,"vega":0.033,"rho":0.0078,"greeksSource":"cboe","greeksMissingReason":null},{"symbol":"DUSL260717C00095000","expiration":"2026-07-17","side":"call","strike":95.0,"bid":2.0,"ask":6.7,"mid":4.35,"last":8.3,"volume":1.0,"openInterest":0.0,"iv":0.98437515625,"delta":0.5864,"gamma":0.0546,"theta":-0.5035,"vega":0.0341,"rho":0.0072,"greeksSource":"cboe","greeksMissingReason":null},{"symbol":"DUSL260717C00105000","expiration":"2026-07-17","side":"call","strike":105.0,"bid":0.0,"ask":4.2,"mid":null,"last":2.85,"volume":null,"openInterest":1.0,"iv":1.3168979467773436,"delta":0.1254,"gamma":0.0294,"theta":-0.2233,"vega":0.0181,"rho":0.0016,"greeksSource":"cboe","greeksMissingReason":null},{"symbol":"DUSL260717C00115000","expiration":"2026-07-17","side":"call","strike":115.0,"bid":0.0,"ask":4.0,"mid":null,"last":2.0,"volume":null,"openInterest":2.0,"iv":1.890625546875,"delta":0.0461,"gamma":0.0098,"theta":-0.123,"vega":0.0084,"rho":0.0006,"greeksSource":"cboe","greeksMissingReason":null},{"symbol":"DUSL260717P00075000","expiration":"2026-07-17","side":"put","strike":75.0,"bid":0.0,"ask":4.0,"mid":null,"last":2.4,"volume":null,"openInterest":1.0,"iv":2.4677772680664063,"delta":-0.071,"gamma":0.0078,"theta":-0.3459,"vega":0.0118,"rho":-0.001,"greeksSource":"cboe","greeksMissingReason":null},{"symbol":"DUSL260717P00080000","expiration":"2026-07-17","side":"put","strike":80.0,"bid":0.0,"ask":4.0,"mid":null,"last":1.5,"volume":2.0,"openInterest":1.0,"iv":2.0136768408203123,"delta":-0.1004,"gamma":0.0119,"theta":-0.4002,"vega":0.0154,"rho":-0.0013,"greeksSource":"cboe","greeksMissingReason":null},{"symbol":"DUSL260717P00082000","expiration":"2026-07-17","side":"put","strike":82.0,"bid":0.0,"ask":0.0,"mid":null,"last":6.04,"volume":1.0,"openInterest":0.0,"iv":0.2500075,"delta":-0.1166,"gamma":0.0143,"theta":-0.4232,"vega":0.0171,"rho":-0.0016,"greeksSource":"cboe","greeksMissingReason":null},{"symbol":"DUSL260717P00083000","expiration":"2026-07-17","side":"put","strike":83.0,"bid":0.0,"ask":4.0,"mid":null,"last":1.8,"volume":2.0,"openInterest":3.0,"iv":1.7451184619140623,"delta":-0.1261,"gamma":0.0157,"theta":-0.435,"vega":0.0181,"rho":-0.0016,"greeksSource":"cboe","greeksMissingReason":null},{"symbol":"DUSL260717P00085000","expiration":"2026-07-17","side":"put","strike":85.0,"bid":0.0,"ask":4.1,"mid":null,"last":1.5,"volume":1.0,"openInterest":2.0,"iv":1.583498176269531,"delta":-0.1484,"gamma":0.019,"theta":-0.4583,"vega":0.0202,"rho":-0.0019,"greeksSource":"cboe","greeksMissingReason":null},{"symbol":"DUSL260717P00090000","expiration":"2026-07-17","side":"put","strike":90.0,"bid":0.0,"ask":4.4,"mid":null,"last":7.11,"volume":6.0,"openInterest":6.0,"iv":1.1689494677734376,"delta":-0.2354,"gamma":0.0322,"theta":-0.5096,"vega":0.0269,"rho":-0.0029,"greeksSource":"cboe","greeksMissingReason":null},{"symbol":"DUSL260717P00093000","expiration":"2026-07-17","side":"put","strike":93.0,"bid":0.0,"ask":4.8,"mid":null,"last":1.1,"volume":1.0,"openInterest":1.0,"iv":0.9238288867187501,"delta":-0.327,"gamma":0.0449,"theta":-0.5216,"vega":0.0316,"rho":-0.0038,"greeksSource":"cboe","greeksMissingReason":null},{"symbol":"DUSL260717P00095000","expiration":"2026-07-17","side":"put","strike":95.0,"bid":0.0,"ask":4.8,"mid":null,"last":5.41,"volume":null,"openInterest":0.0,"iv":0.7016631396484375,"delta":-0.4171,"gamma":0.0551,"theta":-0.5084,"vega":0.0341,"rho":-0.0047,"greeksSource":"cboe","greeksMissingReason":null},{"symbol":"DUSL260821C00098000","expiration":"2026-08-21","side":"call","strike":98.0,"bid":3.9,"ask":11.3,"mid":7.6000000000000005,"last":8.62,"volume":null,"openInterest":3.0,"iv":0.6851838122558593,"delta":0.5297,"gamma":0.0209,"theta":-0.1009,"vega":0.1244,"rho":0.0476,"greeksSource":"cboe","greeksMissingReason":null},{"symbol":"DUSL260821C00099000","expiration":"2026-08-21","side":"call","strike":99.0,"bid":3.5,"ask":10.8,"mid":7.15,"last":9.15,"volume":null,"openInterest":1.0,"iv":0.6817658776855471,"delta":0.5088,"gamma":0.021,"theta":-0.1004,"vega":0.1247,"rho":0.046,"greeksSource":"cboe","greeksMissingReason":null},{"symbol":"DUSL260821P00099000","expiration":"2026-08-21","side":"put","strike":99.0,"bid":4.9,"ask":12.5,"mid":8.7,"last":8.85,"volume":null,"openInterest":1.0,"iv":0.5520064331054688,"delta":-0.507,"gamma":0.0216,"theta":-0.103,"vega":0.124,"rho":-0.0476,"greeksSource":"cboe","greeksMissingReason":null},{"symbol":"DUSL260918C00060000","expiration":"2026-09-18","side":"call","strike":60.0,"bid":35.5,"ask":42.1,"mid":38.8,"last":38.0,"volume":null,"openInterest":2.0,"iv":1.1010787133789064,"delta":0.9176,"gamma":0.0039,"theta":-0.0439,"vega":0.065,"rho":0.0917,"greeksSource":"cboe","greeksMissingReason":null},{"symbol":"DUSL260918C00070000","expiration":"2026-09-18","side":"call","strike":70.0,"bid":0.0,"ask":0.0,"mid":null,"last":16.45,"volume":1.0,"openInterest":0.0,"iv":1.0000000000000003e-05,"delta":0.8658,"gamma":0.0063,"theta":-0.0552,"vega":0.0909,"rho":0.099,"greeksSource":"cboe","greeksMissingReason":null},{"symbol":"DUSL260918C00079000","expiration":"2026-09-18","side":"call","strike":79.0,"bid":15.9,"ask":25.9,"mid":20.9,"last":12.6,"volume":1.0,"openInterest":1.0,"iv":0.6999541723632813,"delta":0.7955,"gamma":0.0093,"theta":-0.0647,"vega":0.1181,"rho":0.1005,"greeksSource":"cboe","greeksMissingReason":null},{"symbol":"DUSL260918C00080000","expiration":"2026-09-18","side":"call","strike":80.0,"bid":11.2,"ask":21.0,"mid":16.1,"last":16.2,"volume":null,"openInterest":2.0,"iv":0.7624535473632813,"delta":0.786,"gamma":0.0097,"theta":-0.0656,"vega":0.1212,"rho":0.1003,"greeksSource":"cboe","greeksMissingReason":null},{"symbol":"DUSL260918C00085000","expiration":"2026-09-18","side":"call","strike":85.0,"bid":14.2,"ask":21.5,"mid":17.85,"last":23.1,"volume":5.0,"openInterest":11.0,"iv":0.7575707836914063,"delta":0.7319,"gamma":0.0117,"theta":-0.0698,"vega":0.1364,"rho":0.0977,"greeksSource":"cboe","greeksMissingReason":null},{"symbol":"DUSL260918C00090000","expiration":"2026-09-18","side":"call","strike":90.0,"bid":10.8,"ask":18.4,"mid":14.6,"last":14.0,"volume":1.0,"openInterest":4.0,"iv":0.7240017834472656,"delta":0.6672,"gamma":0.0136,"theta":-0.0728,"vega":0.15,"rho":0.0926,"greeksSource":"cboe","greeksMissingReason":null},{"symbol":"DUSL260918C00095000","expiration":"2026-09-18","side":"call","strike":95.0,"bid":7.8,"ask":15.6,"mid":11.7,"last":11.0,"volume":1.0,"openInterest":1.0,"iv":0.6942169250488281,"delta":0.593,"gamma":0.0153,"theta":-0.0741,"vega":0.1598,"rho":0.0851,"greeksSource":"cboe","greeksMissingReason":null},{"symbol":"DUSL260918C00100000","expiration":"2026-09-18","side":"call","strike":100.0,"bid":5.3,"ask":13.4,"mid":9.35,"last":10.5,"volume":1.0,"openInterest":3.0,"iv":0.6783479431152344,"delta":0.5131,"gamma":0.0163,"theta":-0.0736,"vega":0.1639,"rho":0.0755,"greeksSource":"cboe","greeksMissingReason":null},{"symbol":"DUSL260918C00110000","expiration":"2026-09-18","side":"call","strike":110.0,"bid":0.0,"ask":0.0,"mid":null,"last":10.0,"volume":null,"openInterest":0.0,"iv":0.062509375,"delta":0.3617,"gamma":0.0156,"theta":-0.0677,"vega":0.1538,"rho":0.0549,"greeksSource":"cboe","greeksMissingReason":null},{"symbol":"DUSL260918C00120000","expiration":"2026-09-18","side":"call","strike":120.0,"bid":0.0,"ask":0.0,"mid":null,"last":2.4,"volume":1.0,"openInterest":0.0,"iv":0.12500875,"delta":0.2507,"gamma":0.0128,"theta":-0.0591,"vega":0.1305,"rho":0.0385,"greeksSource":"cboe","greeksMissingReason":null},{"symbol":"DUSL260918C00125000","expiration":"2026-09-18","side":"call","strike":125.0,"bid":0.0,"ask":0.0,"mid":null,"last":2.4,"volume":1.0,"openInterest":0.0,"iv":0.12500875,"delta":0.2111,"gamma":0.0114,"theta":-0.055,"vega":0.1185,"rho":0.0325,"greeksSource":"cboe","greeksMissingReason":null},{"symbol":"DUSL260918P00050000","expiration":"2026-09-18","side":"put","strike":50.0,"bid":0.1,"ask":8.8,"mid":4.45,"last":4.0,"volume":null,"openInterest":1.0,"iv":1.6354998693847653,"delta":-0.0539,"gamma":0.0024,"theta":-0.0383,"vega":0.0448,"rho":-0.0111,"greeksSource":"cboe","greeksMissingReason":null},{"symbol":"DUSL260918P00065000","expiration":"2026-09-18","side":"put","strike":65.0,"bid":0.0,"ask":4.8,"mid":null,"last":4.2,"volume":4.0,"openInterest":9.0,"iv":0.8906260937499999,"delta":-0.1109,"gamma":0.005,"theta":-0.0535,"vega":0.0775,"rho":-0.022,"greeksSource":"cboe","greeksMissingReason":null},{"symbol":"DUSL260918P00070000","expiration":"2026-09-18","side":"put","strike":70.0,"bid":0.1,"ask":8.1,"mid":4.1,"last":6.2,"volume":1.0,"openInterest":9.0,"iv":0.9440923559570311,"delta":-0.1399,"gamma":0.0064,"theta":-0.0587,"vega":0.0912,"rho":-0.0273,"greeksSource":"cboe","greeksMissingReason":null},{"symbol":"DUSL260918P00075000","expiration":"2026-09-18","side":"put","strike":75.0,"bid":0.2,"ask":7.6,"mid":3.9,"last":2.65,"volume":1.0,"openInterest":7.0,"iv":0.7897970239257812,"delta":-0.176,"gamma":0.008,"theta":-0.0637,"vega":0.1063,"rho":-0.0339,"greeksSource":"cboe","greeksMissingReason":null},{"symbol":"DUSL260918P00078000","expiration":"2026-09-18","side":"put","strike":78.0,"bid":1.6,"ask":11.6,"mid":6.6,"last":8.86,"volume":null,"openInterest":1.0,"iv":0.9323737231445313,"delta":-0.2017,"gamma":0.0091,"theta":-0.0665,"vega":0.1153,"rho":-0.0385,"greeksSource":"cboe","greeksMissingReason":null},{"symbol":"DUSL260918P00080000","expiration":"2026-09-18","side":"put","strike":80.0,"bid":2.1,"ask":12.1,"mid":7.1,"last":10.1,"volume":1.0,"openInterest":1.0,"iv":0.9113778393554688,"delta":-0.2207,"gamma":0.0098,"theta":-0.0683,"vega":0.1216,"rho":-0.0419,"greeksSource":"cboe","greeksMissingReason":null},{"symbol":"DUSL260918P00085000","expiration":"2026-09-18","side":"put","strike":85.0,"bid":0.0,"ask":0.0,"mid":null,"last":9.3,"volume":null,"openInterest":0.0,"iv":0.062509375,"delta":-0.2756,"gamma":0.0118,"theta":-0.0722,"vega":0.1368,"rho":-0.0513,"greeksSource":"cboe","greeksMissingReason":null},{"symbol":"DUSL261218C00085000","expiration":"2026-12-18","side":"call","strike":85.0,"bid":17.0,"ask":24.6,"mid":20.8,"last":20.9,"volume":5.0,"openInterest":10.0,"iv":0.6268958209228517,"delta":0.7053,"gamma":0.0083,"theta":-0.0399,"vega":0.217,"rho":0.1991,"greeksSource":"cboe","greeksMissingReason":null},{"symbol":"DUSL261218C00094000","expiration":"2026-12-18","side":"call","strike":94.0,"bid":7.6,"ask":17.6,"mid":12.600000000000001,"last":14.4,"volume":3.0,"openInterest":3.0,"iv":0.6745638012695314,"delta":0.6178,"gamma":0.0098,"theta":-0.0431,"vega":0.24,"rho":0.1854,"greeksSource":"cboe","greeksMissingReason":null},{"symbol":"DUSL261218C00100000","expiration":"2026-12-18","side":"call","strike":100.0,"bid":9.0,"ask":18.6,"mid":13.8,"last":16.0,"volume":2.0,"openInterest":4.0,"iv":0.6189613299560548,"delta":0.5553,"gamma":0.0105,"theta":-0.0439,"vega":0.2486,"rho":0.1721,"greeksSource":"cboe","greeksMissingReason":null},{"symbol":"DUSL261218C00110000","expiration":"2026-12-18","side":"call","strike":110.0,"bid":0.0,"ask":0.0,"mid":null,"last":8.0,"volume":null,"openInterest":0.0,"iv":0.062509375,"delta":0.4513,"gamma":0.0109,"theta":-0.0432,"vega":0.2492,"rho":0.1459,"greeksSource":"cboe","greeksMissingReason":null},{"symbol":"DUSL261218C00120000","expiration":"2026-12-18","side":"call","strike":120.0,"bid":2.8,"ask":12.8,"mid":7.800000000000001,"last":9.5,"volume":1.0,"openInterest":2.0,"iv":0.6160316717529297,"delta":0.3573,"gamma":0.0105,"theta":-0.0404,"vega":0.2349,"rho":0.1187,"greeksSource":"cboe","greeksMissingReason":null},{"symbol":"DUSL261218C00130000","expiration":"2026-12-18","side":"call","strike":130.0,"bid":1.4,"ask":11.4,"mid":6.4,"last":8.9,"volume":1.0,"openInterest":2.0,"iv":0.641605146484375,"delta":0.2801,"gamma":0.0095,"theta":-0.0366,"vega":0.212,"rho":0.0947,"greeksSource":"cboe","greeksMissingReason":null},{"symbol":"DUSL261218P00060000","expiration":"2026-12-18","side":"put","strike":60.0,"bid":0.4,"ask":9.7,"mid":5.05,"last":2.55,"volume":null,"openInterest":1.0,"iv":0.8786633227539062,"delta":-0.1198,"gamma":0.0039,"theta":-0.0318,"vega":0.1262,"rho":-0.0607,"greeksSource":"cboe","greeksMissingReason":null},{"symbol":"DUSL261218P00065000","expiration":"2026-12-18","side":"put","strike":65.0,"bid":0.0,"ask":0.0,"mid":null,"last":6.1,"volume":null,"openInterest":0.0,"iv":0.12500875,"delta":-0.1465,"gamma":0.0047,"theta":-0.0348,"vega":0.1447,"rho":-0.0735,"greeksSource":"cboe","greeksMissingReason":null},{"symbol":"DUSL261218P00070000","expiration":"2026-12-18","side":"put","strike":70.0,"bid":1.5,"ask":10.9,"mid":6.2,"last":5.4,"volume":1.0,"openInterest":5.0,"iv":0.7432886999511719,"delta":-0.1774,"gamma":0.0056,"theta":-0.0375,"vega":0.1641,"rho":-0.0877,"greeksSource":"cboe","greeksMissingReason":null},{"symbol":"DUSL261218P00075000","expiration":"2026-12-18","side":"put","strike":75.0,"bid":2.4,"ask":11.7,"mid":7.05,"last":7.25,"volume":1.0,"openInterest":2.0,"iv":0.6898224377441409,"delta":-0.2128,"gamma":0.0066,"theta":-0.04,"vega":0.183,"rho":-0.104,"greeksSource":"cboe","greeksMissingReason":null}]}