{"symbol":"LVO","updated":"2026-07-14T21:47:36.460714-04:00","underlyingPrice":5.210000038146973,"greeks":{"enabled":true,"primarySource":"cboe","fallbackSource":"client-black-scholes","riskFreeRate":null,"dividendYield":null,"total":16,"cboeMatched":16,"computed":0,"missing":0,"cboeContracts":38},"expirations":["2026-07-17","2026-10-16","2027-01-15"],"quotes":[{"symbol":"LVO260717C00002500","expiration":"2026-07-17","side":"call","strike":2.5,"bid":2.8,"ask":4.8,"mid":3.8,"last":3.4,"volume":10.0,"openInterest":10.0,"iv":18.21875430664063,"delta":0.9833,"gamma":0.0235,"theta":-0.0083,"vega":0.0002,"rho":0.0004,"greeksSource":"cboe","greeksMissingReason":null},{"symbol":"LVO260717C00005000","expiration":"2026-07-17","side":"call","strike":5.0,"bid":0.0,"ask":1.15,"mid":null,"last":0.3,"volume":1.0,"openInterest":22.0,"iv":2.5156287109374995,"delta":0.5935,"gamma":0.6216,"theta":-0.0322,"vega":0.0021,"rho":0.0004,"greeksSource":"cboe","greeksMissingReason":null},{"symbol":"LVO260717C00007500","expiration":"2026-07-17","side":"call","strike":7.5,"bid":0.0,"ask":0.1,"mid":null,"last":0.1,"volume":15.0,"openInterest":836.0,"iv":2.750003125,"delta":0.0577,"gamma":0.0994,"theta":-0.014,"vega":0.0006,"rho":0.0,"greeksSource":"cboe","greeksMissingReason":null},{"symbol":"LVO260717C00010000","expiration":"2026-07-17","side":"call","strike":10.0,"bid":0.0,"ask":0.05,"mid":null,"last":0.01,"volume":14.0,"openInterest":25.0,"iv":3.750000625,"delta":0.0221,"gamma":0.0331,"theta":-0.0076,"vega":0.0003,"rho":0.0,"greeksSource":"cboe","greeksMissingReason":null},{"symbol":"LVO260717P00002500","expiration":"2026-07-17","side":"put","strike":2.5,"bid":0.0,"ask":0.05,"mid":null,"last":0.15,"volume":null,"openInterest":27.0,"iv":4.687504140625,"delta":-0.0183,"gamma":0.0235,"theta":-0.0086,"vega":0.0002,"rho":0.0,"greeksSource":"cboe","greeksMissingReason":null},{"symbol":"LVO260717P00005000","expiration":"2026-07-17","side":"put","strike":5.0,"bid":0.0,"ask":0.75,"mid":null,"last":0.06,"volume":6.0,"openInterest":631.0,"iv":2.56250359375,"delta":-0.4105,"gamma":0.6265,"theta":-0.0325,"vega":0.0021,"rho":-0.0003,"greeksSource":"cboe","greeksMissingReason":null},{"symbol":"LVO260717P00007500","expiration":"2026-07-17","side":"put","strike":7.5,"bid":1.55,"ask":3.0,"mid":2.275,"last":2.33,"volume":1.0,"openInterest":1.0,"iv":7.1718760351562505,"delta":-0.9472,"gamma":0.1,"theta":-0.0138,"vega":0.0006,"rho":-0.0004,"greeksSource":"cboe","greeksMissingReason":null},{"symbol":"LVO261016C00005000","expiration":"2026-10-16","side":"call","strike":5.0,"bid":0.05,"ask":2.45,"mid":1.25,"last":1.6,"volume":10.0,"openInterest":11.0,"iv":1.119145029296875,"delta":0.6373,"gamma":0.1383,"theta":-0.0053,"vega":0.0099,"rho":0.0055,"greeksSource":"cboe","greeksMissingReason":null},{"symbol":"LVO261016C00007500","expiration":"2026-10-16","side":"call","strike":7.5,"bid":0.0,"ask":0.0,"mid":null,"last":1.36,"volume":2.0,"openInterest":0.0,"iv":0.2500075,"delta":0.3571,"gamma":0.1308,"theta":-0.0055,"vega":0.0097,"rho":0.0034,"greeksSource":"cboe","greeksMissingReason":null},{"symbol":"LVO261016C00010000","expiration":"2026-10-16","side":"call","strike":10.0,"bid":0.0,"ask":1.5,"mid":null,"last":0.7,"volume":1.0,"openInterest":108.0,"iv":1.68359533203125,"delta":0.2168,"gamma":0.0958,"theta":-0.0046,"vega":0.0076,"rho":0.0021,"greeksSource":"cboe","greeksMissingReason":null},{"symbol":"LVO261016P00002500","expiration":"2026-10-16","side":"put","strike":2.5,"bid":0.0,"ask":0.35,"mid":null,"last":0.12,"volume":null,"openInterest":4.0,"iv":1.3554719726562499,"delta":-0.075,"gamma":0.0427,"theta":-0.0024,"vega":0.0037,"rho":-0.0013,"greeksSource":"cboe","greeksMissingReason":null},{"symbol":"LVO261016P00005000","expiration":"2026-10-16","side":"put","strike":5.0,"bid":0.0,"ask":2.25,"mid":null,"last":0.94,"volume":50.0,"openInterest":3.0,"iv":1.2070352148437498,"delta":-0.3726,"gamma":0.1404,"theta":-0.0054,"vega":0.0099,"rho":-0.0062,"greeksSource":"cboe","greeksMissingReason":null},{"symbol":"LVO261016P00007500","expiration":"2026-10-16","side":"put","strike":7.5,"bid":0.0,"ask":0.0,"mid":null,"last":3.3,"volume":null,"openInterest":0.0,"iv":1.0000000000000003e-05,"delta":-0.6591,"gamma":0.1355,"theta":-0.0054,"vega":0.0095,"rho":-0.0107,"greeksSource":"cboe","greeksMissingReason":null},{"symbol":"LVO270115C00007500","expiration":"2027-01-15","side":"call","strike":7.5,"bid":0.0,"ask":0.0,"mid":null,"last":1.72,"volume":null,"openInterest":0.0,"iv":0.12500875,"delta":0.4565,"gamma":0.0926,"theta":-0.0043,"vega":0.014,"rho":0.0063,"greeksSource":"cboe","greeksMissingReason":null},{"symbol":"LVO270115C00010000","expiration":"2027-01-15","side":"call","strike":10.0,"bid":0.05,"ask":1.95,"mid":1.0,"last":0.05,"volume":1.0,"openInterest":127.0,"iv":1.3750031249999999,"delta":0.3614,"gamma":0.0806,"theta":-0.0044,"vega":0.0133,"rho":0.0052,"greeksSource":"cboe","greeksMissingReason":null},{"symbol":"LVO270115P00005000","expiration":"2027-01-15","side":"put","strike":5.0,"bid":0.05,"ask":2.6,"mid":1.325,"last":0.9,"volume":null,"openInterest":1.0,"iv":1.0058643457031249,"delta":-0.3365,"gamma":0.0917,"theta":-0.0036,"vega":0.013,"rho":-0.0142,"greeksSource":"cboe","greeksMissingReason":null}]}