{"symbol":"RBA","updated":"2026-07-15T00:44:42.062364-04:00","underlyingPrice":109.16000366210938,"greeks":{"enabled":true,"primarySource":"cboe","fallbackSource":"client-black-scholes","riskFreeRate":null,"dividendYield":null,"total":86,"cboeMatched":86,"computed":0,"missing":0,"cboeContracts":202},"expirations":["2026-07-17","2026-08-21","2026-09-18","2026-12-18"],"quotes":[{"symbol":"RBA260717C00095000","expiration":"2026-07-17","side":"call","strike":95.0,"bid":0.0,"ask":0.0,"mid":null,"last":17.3,"volume":2.0,"openInterest":0.0,"iv":1.0000000000000003e-05,"delta":0.976,"gamma":0.0075,"theta":-0.0543,"vega":0.0055,"rho":0.0043,"greeksSource":"cboe","greeksMissingReason":null},{"symbol":"RBA260717C00100000","expiration":"2026-07-17","side":"call","strike":100.0,"bid":0.0,"ask":0.0,"mid":null,"last":16.0,"volume":2.0,"openInterest":0.0,"iv":1.0000000000000003e-05,"delta":0.9454,"gamma":0.0184,"theta":-0.0948,"vega":0.011,"rho":0.0056,"greeksSource":"cboe","greeksMissingReason":null},{"symbol":"RBA260717C00105000","expiration":"2026-07-17","side":"call","strike":105.0,"bid":0.0,"ask":0.0,"mid":null,"last":3.98,"volume":3.0,"openInterest":0.0,"iv":1.0000000000000003e-05,"delta":0.8418,"gamma":0.0557,"theta":-0.1736,"vega":0.024,"rho":0.007,"greeksSource":"cboe","greeksMissingReason":null},{"symbol":"RBA260717C00110000","expiration":"2026-07-17","side":"call","strike":110.0,"bid":0.0,"ask":0.0,"mid":null,"last":1.18,"volume":8.0,"openInterest":0.0,"iv":0.0312596875,"delta":0.4077,"gamma":0.1217,"theta":-0.2242,"vega":0.0386,"rho":0.0051,"greeksSource":"cboe","greeksMissingReason":null},{"symbol":"RBA260717C00115000","expiration":"2026-07-17","side":"call","strike":115.0,"bid":0.0,"ask":0.0,"mid":null,"last":1.09,"volume":285.0,"openInterest":0.0,"iv":0.12500875,"delta":0.0905,"gamma":0.0391,"theta":-0.0998,"vega":0.0164,"rho":0.0013,"greeksSource":"cboe","greeksMissingReason":null},{"symbol":"RBA260717C00120000","expiration":"2026-07-17","side":"call","strike":120.0,"bid":0.0,"ask":0.0,"mid":null,"last":2.14,"volume":2.0,"openInterest":0.0,"iv":0.2500075,"delta":0.0317,"gamma":0.013,"theta":-0.0478,"vega":0.0072,"rho":0.0004,"greeksSource":"cboe","greeksMissingReason":null},{"symbol":"RBA260717C00125000","expiration":"2026-07-17","side":"call","strike":125.0,"bid":0.0,"ask":0.0,"mid":null,"last":0.43,"volume":null,"openInterest":0.0,"iv":0.2500075,"delta":0.0148,"gamma":0.0056,"theta":-0.0268,"vega":0.0037,"rho":0.0002,"greeksSource":"cboe","greeksMissingReason":null},{"symbol":"RBA260717C00130000","expiration":"2026-07-17","side":"call","strike":130.0,"bid":0.0,"ask":0.0,"mid":null,"last":0.33,"volume":null,"openInterest":0.0,"iv":0.500005,"delta":0.0081,"gamma":0.0028,"theta":-0.0167,"vega":0.0022,"rho":0.0001,"greeksSource":"cboe","greeksMissingReason":null},{"symbol":"RBA260717C00155000","expiration":"2026-07-17","side":"call","strike":155.0,"bid":null,"ask":0.0,"mid":null,"last":0.18,"volume":3.0,"openInterest":0.0,"iv":0.500005,"delta":0.0012,"gamma":0.0003,"theta":-0.0034,"vega":0.0004,"rho":0.0,"greeksSource":"cboe","greeksMissingReason":null},{"symbol":"RBA260717P00065000","expiration":"2026-07-17","side":"put","strike":65.0,"bid":0.0,"ask":0.75,"mid":null,"last":0.5,"volume":null,"openInterest":1.0,"iv":3.2265644335937496,"delta":-0.0012,"gamma":0.0002,"theta":-0.0058,"vega":0.0004,"rho":0.0,"greeksSource":"cboe","greeksMissingReason":null},{"symbol":"RBA260717P00080000","expiration":"2026-07-17","side":"put","strike":80.0,"bid":0.0,"ask":0.0,"mid":null,"last":0.45,"volume":null,"openInterest":0.0,"iv":0.500005,"delta":-0.0044,"gamma":0.001,"theta":-0.0158,"vega":0.0013,"rho":-0.0001,"greeksSource":"cboe","greeksMissingReason":null},{"symbol":"RBA260717P00085000","expiration":"2026-07-17","side":"put","strike":85.0,"bid":0.0,"ask":1.4,"mid":null,"last":0.55,"volume":null,"openInterest":1.0,"iv":2.02344244140625,"delta":-0.0074,"gamma":0.0018,"theta":-0.0232,"vega":0.002,"rho":-0.0001,"greeksSource":"cboe","greeksMissingReason":null},{"symbol":"RBA260717P00090000","expiration":"2026-07-17","side":"put","strike":90.0,"bid":0.95,"ask":2.15,"mid":1.5499999999999998,"last":2.3,"volume":4.0,"openInterest":6.0,"iv":2.1103562866210934,"delta":-0.013,"gamma":0.0034,"theta":-0.0353,"vega":0.0033,"rho":-0.0002,"greeksSource":"cboe","greeksMissingReason":null},{"symbol":"RBA260717P00092500","expiration":"2026-07-17","side":"put","strike":92.5,"bid":1.4,"ask":2.25,"mid":1.825,"last":3.1,"volume":null,"openInterest":21.0,"iv":2.0185596411132813,"delta":-0.0179,"gamma":0.005,"theta":-0.0442,"vega":0.0044,"rho":-0.0003,"greeksSource":"cboe","greeksMissingReason":null},{"symbol":"RBA260717P00095000","expiration":"2026-07-17","side":"put","strike":95.0,"bid":1.85,"ask":2.75,"mid":2.3,"last":3.6,"volume":null,"openInterest":13.0,"iv":1.9819336840820312,"delta":-0.0252,"gamma":0.0074,"theta":-0.0562,"vega":0.0059,"rho":-0.0004,"greeksSource":"cboe","greeksMissingReason":null},{"symbol":"RBA260717P00097500","expiration":"2026-07-17","side":"put","strike":97.5,"bid":0.0,"ask":0.0,"mid":null,"last":1.14,"volume":64.0,"openInterest":0.0,"iv":0.2500075,"delta":-0.0367,"gamma":0.0114,"theta":-0.0727,"vega":0.008,"rho":-0.0006,"greeksSource":"cboe","greeksMissingReason":null},{"symbol":"RBA260717P00100000","expiration":"2026-07-17","side":"put","strike":100.0,"bid":0.0,"ask":0.0,"mid":null,"last":0.95,"volume":11.0,"openInterest":0.0,"iv":0.2500075,"delta":-0.056,"gamma":0.0183,"theta":-0.0957,"vega":0.0113,"rho":-0.0008,"greeksSource":"cboe","greeksMissingReason":null},{"symbol":"RBA260717P00105000","expiration":"2026-07-17","side":"put","strike":105.0,"bid":0.0,"ask":0.0,"mid":null,"last":0.51,"volume":1.0,"openInterest":0.0,"iv":0.12500875,"delta":-0.16,"gamma":0.0554,"theta":-0.1732,"vega":0.0243,"rho":-0.0024,"greeksSource":"cboe","greeksMissingReason":null},{"symbol":"RBA260717P00110000","expiration":"2026-07-17","side":"put","strike":110.0,"bid":0.0,"ask":0.0,"mid":null,"last":4.59,"volume":1.0,"openInterest":0.0,"iv":1.0000000000000003e-05,"delta":-0.5925,"gamma":0.1212,"theta":-0.2231,"vega":0.0386,"rho":-0.0091,"greeksSource":"cboe","greeksMissingReason":null},{"symbol":"RBA260717P00115000","expiration":"2026-07-17","side":"put","strike":115.0,"bid":0.0,"ask":0.0,"mid":null,"last":6.2,"volume":null,"openInterest":0.0,"iv":1.0000000000000003e-05,"delta":-0.9086,"gamma":0.0391,"theta":-0.099,"vega":0.0164,"rho":-0.0144,"greeksSource":"cboe","greeksMissingReason":null},{"symbol":"RBA260821C00105000","expiration":"2026-08-21","side":"call","strike":105.0,"bid":0.0,"ask":0.0,"mid":null,"last":6.6,"volume":1.0,"openInterest":0.0,"iv":1.0000000000000003e-05,"delta":0.6633,"gamma":0.0297,"theta":-0.0578,"vega":0.1283,"rho":0.0714,"greeksSource":"cboe","greeksMissingReason":null},{"symbol":"RBA260821C00115000","expiration":"2026-08-21","side":"call","strike":115.0,"bid":0.0,"ask":0.0,"mid":null,"last":2.1,"volume":10.0,"openInterest":0.0,"iv":0.0312596875,"delta":0.339,"gamma":0.0316,"theta":-0.0553,"vega":0.1291,"rho":0.0378,"greeksSource":"cboe","greeksMissingReason":null},{"symbol":"RBA260821C00120000","expiration":"2026-08-21","side":"call","strike":120.0,"bid":0.0,"ask":0.0,"mid":null,"last":1.1,"volume":1.0,"openInterest":0.0,"iv":0.062509375,"delta":0.2244,"gamma":0.0242,"theta":-0.0481,"vega":0.106,"rho":0.025,"greeksSource":"cboe","greeksMissingReason":null},{"symbol":"RBA260821C00125000","expiration":"2026-08-21","side":"call","strike":125.0,"bid":0.0,"ask":0.0,"mid":null,"last":1.24,"volume":1.0,"openInterest":0.0,"iv":0.12500875,"delta":0.1538,"gamma":0.0176,"theta":-0.0411,"vega":0.0842,"rho":0.0171,"greeksSource":"cboe","greeksMissingReason":null},{"symbol":"RBA260918C00080000","expiration":"2026-09-18","side":"call","strike":80.0,"bid":0.0,"ask":0.0,"mid":null,"last":26.48,"volume":1.0,"openInterest":0.0,"iv":1.0000000000000003e-05,"delta":0.9482,"gamma":0.0047,"theta":-0.0148,"vega":0.0485,"rho":0.1,"greeksSource":"cboe","greeksMissingReason":null},{"symbol":"RBA260918C00087500","expiration":"2026-09-18","side":"call","strike":87.5,"bid":16.0,"ask":18.0,"mid":17.0,"last":18.4,"volume":null,"openInterest":1.0,"iv":1.0000000000000003e-05,"delta":0.9101,"gamma":0.0083,"theta":-0.0218,"vega":0.0756,"rho":0.1117,"greeksSource":"cboe","greeksMissingReason":null},{"symbol":"RBA260918C00090000","expiration":"2026-09-18","side":"call","strike":90.0,"bid":13.8,"ask":16.4,"mid":15.1,"last":16.5,"volume":null,"openInterest":3.0,"iv":1.0000000000000003e-05,"delta":0.8912,"gamma":0.01,"theta":-0.0244,"vega":0.0859,"rho":0.1115,"greeksSource":"cboe","greeksMissingReason":null},{"symbol":"RBA260918C00092500","expiration":"2026-09-18","side":"call","strike":92.5,"bid":12.1,"ask":14.2,"mid":13.149999999999999,"last":14.75,"volume":null,"openInterest":1.0,"iv":1.0000000000000003e-05,"delta":0.8679,"gamma":0.012,"theta":-0.0272,"vega":0.0993,"rho":0.1153,"greeksSource":"cboe","greeksMissingReason":null},{"symbol":"RBA260918C00095000","expiration":"2026-09-18","side":"call","strike":95.0,"bid":10.4,"ask":12.4,"mid":11.4,"last":13.15,"volume":null,"openInterest":0.0,"iv":1.0000000000000003e-05,"delta":0.8392,"gamma":0.0144,"theta":-0.0301,"vega":0.1134,"rho":0.1164,"greeksSource":"cboe","greeksMissingReason":null},{"symbol":"RBA260918C00097500","expiration":"2026-09-18","side":"call","strike":97.5,"bid":8.7,"ask":10.6,"mid":9.649999999999999,"last":12.7,"volume":1.0,"openInterest":3.0,"iv":1.0000000000000003e-05,"delta":0.804,"gamma":0.017,"theta":-0.0329,"vega":0.1277,"rho":0.1147,"greeksSource":"cboe","greeksMissingReason":null},{"symbol":"RBA260918C00100000","expiration":"2026-09-18","side":"call","strike":100.0,"bid":0.0,"ask":0.0,"mid":null,"last":10.53,"volume":8.0,"openInterest":0.0,"iv":1.0000000000000003e-05,"delta":0.7612,"gamma":0.0199,"theta":-0.0357,"vega":0.1434,"rho":0.1143,"greeksSource":"cboe","greeksMissingReason":null},{"symbol":"RBA260918C00105000","expiration":"2026-09-18","side":"call","strike":105.0,"bid":0.0,"ask":0.0,"mid":null,"last":9.53,"volume":2.0,"openInterest":0.0,"iv":1.0000000000000003e-05,"delta":0.6508,"gamma":0.0254,"theta":-0.0402,"vega":0.1712,"rho":0.1064,"greeksSource":"cboe","greeksMissingReason":null},{"symbol":"RBA260918C00110000","expiration":"2026-09-18","side":"call","strike":110.0,"bid":0.0,"ask":0.0,"mid":null,"last":8.19,"volume":2.0,"openInterest":0.0,"iv":0.0039162109375,"delta":0.5148,"gamma":0.0284,"theta":-0.0419,"vega":0.1843,"rho":0.0894,"greeksSource":"cboe","greeksMissingReason":null},{"symbol":"RBA260918C00115000","expiration":"2026-09-18","side":"call","strike":115.0,"bid":0.0,"ask":0.0,"mid":null,"last":6.43,"volume":1.0,"openInterest":0.0,"iv":0.0312596875,"delta":0.3802,"gamma":0.027,"theta":-0.0403,"vega":0.1764,"rho":0.0686,"greeksSource":"cboe","greeksMissingReason":null},{"symbol":"RBA260918C00120000","expiration":"2026-09-18","side":"call","strike":120.0,"bid":0.0,"ask":0.0,"mid":null,"last":3.3,"volume":1.0,"openInterest":0.0,"iv":0.062509375,"delta":0.2722,"gamma":0.0227,"theta":-0.0363,"vega":0.1543,"rho":0.0502,"greeksSource":"cboe","greeksMissingReason":null},{"symbol":"RBA260918C00125000","expiration":"2026-09-18","side":"call","strike":125.0,"bid":0.0,"ask":0.0,"mid":null,"last":2.48,"volume":2.0,"openInterest":0.0,"iv":0.062509375,"delta":0.1957,"gamma":0.0179,"theta":-0.0317,"vega":0.1288,"rho":0.0364,"greeksSource":"cboe","greeksMissingReason":null},{"symbol":"RBA260918C00130000","expiration":"2026-09-18","side":"call","strike":130.0,"bid":0.0,"ask":0.0,"mid":null,"last":2.15,"volume":1.0,"openInterest":0.0,"iv":0.12500875,"delta":0.1435,"gamma":0.0139,"theta":-0.0274,"vega":0.1058,"rho":0.0267,"greeksSource":"cboe","greeksMissingReason":null},{"symbol":"RBA260918C00135000","expiration":"2026-09-18","side":"call","strike":135.0,"bid":0.05,"ask":1.4,"mid":0.725,"last":0.95,"volume":2.0,"openInterest":7.0,"iv":0.43555251953125,"delta":0.1079,"gamma":0.0107,"theta":-0.0236,"vega":0.0868,"rho":0.0201,"greeksSource":"cboe","greeksMissingReason":null},{"symbol":"RBA260918C00140000","expiration":"2026-09-18","side":"call","strike":140.0,"bid":0.0,"ask":0.0,"mid":null,"last":0.45,"volume":4.0,"openInterest":0.0,"iv":0.12500875,"delta":0.083,"gamma":0.0084,"theta":-0.0205,"vega":0.0717,"rho":0.0154,"greeksSource":"cboe","greeksMissingReason":null},{"symbol":"RBA260918C00150000","expiration":"2026-09-18","side":"call","strike":150.0,"bid":0.0,"ask":0.0,"mid":null,"last":1.85,"volume":1.0,"openInterest":0.0,"iv":0.12500875,"delta":0.0523,"gamma":0.0053,"theta":-0.0156,"vega":0.0502,"rho":0.0097,"greeksSource":"cboe","greeksMissingReason":null},{"symbol":"RBA260918C00160000","expiration":"2026-09-18","side":"call","strike":160.0,"bid":0.0,"ask":0.0,"mid":null,"last":0.2,"volume":4.0,"openInterest":0.0,"iv":0.2500075,"delta":0.0352,"gamma":0.0036,"theta":-0.0122,"vega":0.0365,"rho":0.0065,"greeksSource":"cboe","greeksMissingReason":null},{"symbol":"RBA260918C00165000","expiration":"2026-09-18","side":"call","strike":165.0,"bid":0.0,"ask":0.0,"mid":null,"last":0.2,"volume":2.0,"openInterest":0.0,"iv":0.2500075,"delta":0.0294,"gamma":0.003,"theta":-0.0109,"vega":0.0315,"rho":0.0054,"greeksSource":"cboe","greeksMissingReason":null},{"symbol":"RBA260918C00170000","expiration":"2026-09-18","side":"call","strike":170.0,"bid":0.0,"ask":0.0,"mid":null,"last":0.25,"volume":2.0,"openInterest":0.0,"iv":0.2500075,"delta":0.0249,"gamma":0.0025,"theta":-0.0098,"vega":0.0274,"rho":0.0046,"greeksSource":"cboe","greeksMissingReason":null},{"symbol":"RBA260918P00065000","expiration":"2026-09-18","side":"put","strike":65.0,"bid":0.0,"ask":0.0,"mid":null,"last":0.5,"volume":10.0,"openInterest":0.0,"iv":0.2500075,"delta":-0.0199,"gamma":0.0016,"theta":-0.0105,"vega":0.0226,"rho":-0.0042,"greeksSource":"cboe","greeksMissingReason":null},{"symbol":"RBA260918P00085000","expiration":"2026-09-18","side":"put","strike":85.0,"bid":0.0,"ask":0.0,"mid":null,"last":4.55,"volume":12.0,"openInterest":0.0,"iv":0.12500875,"delta":-0.0769,"gamma":0.007,"theta":-0.0223,"vega":0.0674,"rho":-0.0156,"greeksSource":"cboe","greeksMissingReason":null},{"symbol":"RBA260918P00087500","expiration":"2026-09-18","side":"put","strike":87.5,"bid":1.85,"ask":2.95,"mid":2.4000000000000004,"last":3.3,"volume":null,"openInterest":3.0,"iv":0.5778850805664062,"delta":-0.0924,"gamma":0.0084,"theta":-0.0244,"vega":0.0774,"rho":-0.0186,"greeksSource":"cboe","greeksMissingReason":null},{"symbol":"RBA260918P00090000","expiration":"2026-09-18","side":"put","strike":90.0,"bid":0.0,"ask":0.0,"mid":null,"last":1.24,"volume":1.0,"openInterest":0.0,"iv":0.12500875,"delta":-0.1113,"gamma":0.0101,"theta":-0.0268,"vega":0.0886,"rho":-0.0225,"greeksSource":"cboe","greeksMissingReason":null},{"symbol":"RBA260918P00092500","expiration":"2026-09-18","side":"put","strike":92.5,"bid":0.0,"ask":0.0,"mid":null,"last":1.78,"volume":45.0,"openInterest":0.0,"iv":0.062509375,"delta":-0.1347,"gamma":0.0121,"theta":-0.0292,"vega":0.1011,"rho":-0.0269,"greeksSource":"cboe","greeksMissingReason":null},{"symbol":"RBA260918P00095000","expiration":"2026-09-18","side":"put","strike":95.0,"bid":0.0,"ask":0.0,"mid":null,"last":1.86,"volume":1.0,"openInterest":0.0,"iv":0.062509375,"delta":-0.1634,"gamma":0.0144,"theta":-0.0318,"vega":0.115,"rho":-0.0324,"greeksSource":"cboe","greeksMissingReason":null},{"symbol":"RBA260918P00100000","expiration":"2026-09-18","side":"put","strike":100.0,"bid":0.0,"ask":0.0,"mid":null,"last":3.43,"volume":45.0,"openInterest":0.0,"iv":0.062509375,"delta":-0.2416,"gamma":0.02,"theta":-0.0369,"vega":0.1449,"rho":-0.0473,"greeksSource":"cboe","greeksMissingReason":null},{"symbol":"RBA260918P00105000","expiration":"2026-09-18","side":"put","strike":105.0,"bid":0.0,"ask":0.0,"mid":null,"last":6.16,"volume":null,"openInterest":0.0,"iv":0.0312596875,"delta":-0.3527,"gamma":0.0256,"theta":-0.041,"vega":0.1719,"rho":-0.0672,"greeksSource":"cboe","greeksMissingReason":null},{"symbol":"RBA260918P00110000","expiration":"2026-09-18","side":"put","strike":110.0,"bid":10.7,"ask":12.7,"mid":11.7,"last":13.0,"volume":2.0,"openInterest":4.0,"iv":0.6082802844238282,"delta":-0.4898,"gamma":0.0286,"theta":-0.0423,"vega":0.1842,"rho":-0.0911,"greeksSource":"cboe","greeksMissingReason":null},{"symbol":"RBA261218C00070000","expiration":"2026-12-18","side":"call","strike":70.0,"bid":0.0,"ask":0.0,"mid":null,"last":47.63,"volume":null,"openInterest":0.0,"iv":1.0000000000000003e-05,"delta":0.9561,"gamma":0.0029,"theta":0.0,"vega":0.066,"rho":0.2413,"greeksSource":"cboe","greeksMissingReason":null},{"symbol":"RBA261218C00075000","expiration":"2026-12-18","side":"call","strike":75.0,"bid":26.5,"ask":29.0,"mid":27.75,"last":41.66,"volume":null,"openInterest":11.0,"iv":1.0000000000000003e-05,"delta":0.9393,"gamma":0.004,"theta":-0.0027,"vega":0.0859,"rho":0.2543,"greeksSource":"cboe","greeksMissingReason":null},{"symbol":"RBA261218C00080000","expiration":"2026-12-18","side":"call","strike":80.0,"bid":24.1,"ask":26.0,"mid":25.05,"last":25.9,"volume":null,"openInterest":1.0,"iv":1.0000000000000003e-05,"delta":0.9162,"gamma":0.0055,"theta":-0.0062,"vega":0.1102,"rho":0.2647,"greeksSource":"cboe","greeksMissingReason":null},{"symbol":"RBA261218C00085000","expiration":"2026-12-18","side":"call","strike":85.0,"bid":19.6,"ask":22.3,"mid":20.950000000000003,"last":22.2,"volume":null,"openInterest":1.0,"iv":1.0000000000000003e-05,"delta":0.8847,"gamma":0.0073,"theta":-0.0099,"vega":0.139,"rho":0.2714,"greeksSource":"cboe","greeksMissingReason":null},{"symbol":"RBA261218C00090000","expiration":"2026-12-18","side":"call","strike":90.0,"bid":16.3,"ask":18.4,"mid":17.35,"last":18.5,"volume":null,"openInterest":1.0,"iv":1.0000000000000003e-05,"delta":0.8427,"gamma":0.0096,"theta":-0.0137,"vega":0.1718,"rho":0.2729,"greeksSource":"cboe","greeksMissingReason":null},{"symbol":"RBA261218C00092500","expiration":"2026-12-18","side":"call","strike":92.5,"bid":14.6,"ask":16.7,"mid":15.649999999999999,"last":16.8,"volume":null,"openInterest":1.0,"iv":0.11426666992187501,"delta":0.817,"gamma":0.0108,"theta":-0.0156,"vega":0.1889,"rho":0.2692,"greeksSource":"cboe","greeksMissingReason":null},{"symbol":"RBA261218C00095000","expiration":"2026-12-18","side":"call","strike":95.0,"bid":0.0,"ask":0.0,"mid":null,"last":16.84,"volume":2.0,"openInterest":0.0,"iv":1.0000000000000003e-05,"delta":0.7879,"gamma":0.0122,"theta":-0.0175,"vega":0.2065,"rho":0.2677,"greeksSource":"cboe","greeksMissingReason":null},{"symbol":"RBA261218C00097500","expiration":"2026-12-18","side":"call","strike":97.5,"bid":11.4,"ask":13.6,"mid":12.5,"last":13.8,"volume":null,"openInterest":7.0,"iv":0.22480023254394527,"delta":0.7554,"gamma":0.0135,"theta":-0.0193,"vega":0.2238,"rho":0.2646,"greeksSource":"cboe","greeksMissingReason":null},{"symbol":"RBA261218C00100000","expiration":"2026-12-18","side":"call","strike":100.0,"bid":0.0,"ask":0.0,"mid":null,"last":18.5,"volume":10.0,"openInterest":0.0,"iv":1.0000000000000003e-05,"delta":0.7194,"gamma":0.0148,"theta":-0.0209,"vega":0.24,"rho":0.2586,"greeksSource":"cboe","greeksMissingReason":null},{"symbol":"RBA261218C00105000","expiration":"2026-12-18","side":"call","strike":105.0,"bid":0.0,"ask":0.0,"mid":null,"last":10.55,"volume":14.0,"openInterest":0.0,"iv":1.0000000000000003e-05,"delta":0.6383,"gamma":0.017,"theta":-0.0235,"vega":0.2666,"rho":0.2383,"greeksSource":"cboe","greeksMissingReason":null},{"symbol":"RBA261218C00110000","expiration":"2026-12-18","side":"call","strike":110.0,"bid":0.0,"ask":0.0,"mid":null,"last":11.9,"volume":6.0,"openInterest":0.0,"iv":0.0039162109375,"delta":0.5488,"gamma":0.0184,"theta":-0.0249,"vega":0.2816,"rho":0.2141,"greeksSource":"cboe","greeksMissingReason":null},{"symbol":"RBA261218C00115000","expiration":"2026-12-18","side":"call","strike":115.0,"bid":0.0,"ask":0.0,"mid":null,"last":9.15,"volume":6.0,"openInterest":0.0,"iv":0.015634843750000002,"delta":0.458,"gamma":0.0187,"theta":-0.0251,"vega":0.2823,"rho":0.1855,"greeksSource":"cboe","greeksMissingReason":null},{"symbol":"RBA261218C00120000","expiration":"2026-12-18","side":"call","strike":120.0,"bid":0.0,"ask":0.0,"mid":null,"last":8.17,"volume":2.0,"openInterest":0.0,"iv":0.0312596875,"delta":0.3728,"gamma":0.0179,"theta":-0.0242,"vega":0.2697,"rho":0.156,"greeksSource":"cboe","greeksMissingReason":null},{"symbol":"RBA261218C00125000","expiration":"2026-12-18","side":"call","strike":125.0,"bid":0.0,"ask":0.0,"mid":null,"last":5.55,"volume":2.0,"openInterest":0.0,"iv":0.062509375,"delta":0.2984,"gamma":0.0163,"theta":-0.0225,"vega":0.2478,"rho":0.126,"greeksSource":"cboe","greeksMissingReason":null},{"symbol":"RBA261218C00130000","expiration":"2026-12-18","side":"call","strike":130.0,"bid":1.35,"ask":3.5,"mid":2.425,"last":3.1,"volume":16.0,"openInterest":16.0,"iv":0.3497379479980468,"delta":0.2371,"gamma":0.0143,"theta":-0.0204,"vega":0.2213,"rho":0.1007,"greeksSource":"cboe","greeksMissingReason":null},{"symbol":"RBA261218C00135000","expiration":"2026-12-18","side":"call","strike":135.0,"bid":0.0,"ask":0.0,"mid":null,"last":3.0,"volume":8.0,"openInterest":0.0,"iv":0.062509375,"delta":0.1872,"gamma":0.0122,"theta":-0.0181,"vega":0.1931,"rho":0.0798,"greeksSource":"cboe","greeksMissingReason":null},{"symbol":"RBA261218C00145000","expiration":"2026-12-18","side":"call","strike":145.0,"bid":0.0,"ask":0.0,"mid":null,"last":1.9,"volume":null,"openInterest":0.0,"iv":0.12500875,"delta":0.1184,"gamma":0.0086,"theta":-0.0139,"vega":0.1431,"rho":0.0506,"greeksSource":"cboe","greeksMissingReason":null},{"symbol":"RBA261218C00150000","expiration":"2026-12-18","side":"call","strike":150.0,"bid":0.6,"ask":3.3,"mid":1.95,"last":2.01,"volume":1.0,"openInterest":3.0,"iv":0.481450498046875,"delta":0.095,"gamma":0.0072,"theta":-0.0121,"vega":0.1225,"rho":0.0406,"greeksSource":"cboe","greeksMissingReason":null},{"symbol":"RBA261218C00165000","expiration":"2026-12-18","side":"call","strike":165.0,"bid":0.0,"ask":0.0,"mid":null,"last":0.8,"volume":null,"openInterest":0.0,"iv":0.12500875,"delta":0.0516,"gamma":0.0042,"theta":-0.008,"vega":0.0771,"rho":0.022,"greeksSource":"cboe","greeksMissingReason":null},{"symbol":"RBA261218C00170000","expiration":"2026-12-18","side":"call","strike":170.0,"bid":0.0,"ask":0.0,"mid":null,"last":0.55,"volume":2.0,"openInterest":0.0,"iv":0.12500875,"delta":0.0428,"gamma":0.0036,"theta":-0.007,"vega":0.0664,"rho":0.0182,"greeksSource":"cboe","greeksMissingReason":null},{"symbol":"RBA261218C00175000","expiration":"2026-12-18","side":"call","strike":175.0,"bid":0.0,"ask":0.0,"mid":null,"last":0.4,"volume":18.0,"openInterest":0.0,"iv":0.12500875,"delta":0.0357,"gamma":0.003,"theta":-0.0062,"vega":0.0575,"rho":0.0152,"greeksSource":"cboe","greeksMissingReason":null},{"symbol":"RBA261218P00070000","expiration":"2026-12-18","side":"put","strike":70.0,"bid":0.0,"ask":0.0,"mid":null,"last":0.4,"volume":null,"openInterest":0.0,"iv":0.12500875,"delta":-0.0443,"gamma":0.003,"theta":-0.0092,"vega":0.0675,"rho":-0.0223,"greeksSource":"cboe","greeksMissingReason":null},{"symbol":"RBA261218P00075000","expiration":"2026-12-18","side":"put","strike":75.0,"bid":0.0,"ask":0.0,"mid":null,"last":0.75,"volume":1.0,"openInterest":0.0,"iv":0.12500875,"delta":-0.0614,"gamma":0.0041,"theta":-0.0112,"vega":0.0874,"rho":-0.0308,"greeksSource":"cboe","greeksMissingReason":null},{"symbol":"RBA261218P00080000","expiration":"2026-12-18","side":"put","strike":80.0,"bid":0.0,"ask":0.0,"mid":null,"last":3.9,"volume":null,"openInterest":0.0,"iv":0.12500875,"delta":-0.0848,"gamma":0.0055,"theta":-0.0135,"vega":0.1119,"rho":-0.0423,"greeksSource":"cboe","greeksMissingReason":null},{"symbol":"RBA261218P00085000","expiration":"2026-12-18","side":"put","strike":85.0,"bid":0.0,"ask":0.0,"mid":null,"last":2.65,"volume":1.0,"openInterest":0.0,"iv":0.062509375,"delta":-0.1165,"gamma":0.0074,"theta":-0.016,"vega":0.1408,"rho":-0.0579,"greeksSource":"cboe","greeksMissingReason":null},{"symbol":"RBA261218P00090000","expiration":"2026-12-18","side":"put","strike":90.0,"bid":3.8,"ask":5.4,"mid":4.6,"last":4.95,"volume":null,"openInterest":2.0,"iv":0.493291199951172,"delta":-0.159,"gamma":0.0097,"theta":-0.0188,"vega":0.1736,"rho":-0.0783,"greeksSource":"cboe","greeksMissingReason":null},{"symbol":"RBA261218P00092500","expiration":"2026-12-18","side":"put","strike":92.5,"bid":2.8,"ask":6.1,"mid":4.449999999999999,"last":5.15,"volume":null,"openInterest":2.0,"iv":0.4858449853515625,"delta":-0.1849,"gamma":0.011,"theta":-0.0201,"vega":0.1911,"rho":-0.0905,"greeksSource":"cboe","greeksMissingReason":null},{"symbol":"RBA261218P00097500","expiration":"2026-12-18","side":"put","strike":97.5,"bid":0.0,"ask":0.0,"mid":null,"last":9.4,"volume":null,"openInterest":0.0,"iv":0.0312596875,"delta":-0.2474,"gamma":0.0137,"theta":-0.0227,"vega":0.2256,"rho":-0.1191,"greeksSource":"cboe","greeksMissingReason":null},{"symbol":"RBA261218P00100000","expiration":"2026-12-18","side":"put","strike":100.0,"bid":0.0,"ask":0.0,"mid":null,"last":6.1,"volume":80.0,"openInterest":0.0,"iv":0.0312596875,"delta":-0.2834,"gamma":0.015,"theta":-0.0238,"vega":0.2413,"rho":-0.1354,"greeksSource":"cboe","greeksMissingReason":null},{"symbol":"RBA261218P00105000","expiration":"2026-12-18","side":"put","strike":105.0,"bid":0.0,"ask":0.0,"mid":null,"last":5.6,"volume":2.0,"openInterest":0.0,"iv":0.015634843750000002,"delta":-0.3669,"gamma":0.0175,"theta":-0.0254,"vega":0.2676,"rho":-0.1702,"greeksSource":"cboe","greeksMissingReason":null},{"symbol":"RBA261218P00110000","expiration":"2026-12-18","side":"put","strike":110.0,"bid":0.0,"ask":0.0,"mid":null,"last":8.5,"volume":null,"openInterest":0.0,"iv":1.0000000000000003e-05,"delta":-0.4593,"gamma":0.0191,"theta":-0.026,"vega":0.2812,"rho":-0.204,"greeksSource":"cboe","greeksMissingReason":null},{"symbol":"RBA261218P00115000","expiration":"2026-12-18","side":"put","strike":115.0,"bid":0.0,"ask":0.0,"mid":null,"last":8.55,"volume":2.0,"openInterest":0.0,"iv":1.0000000000000003e-05,"delta":-0.5546,"gamma":0.0197,"theta":-0.0254,"vega":0.2795,"rho":-0.2318,"greeksSource":"cboe","greeksMissingReason":null},{"symbol":"RBA261218P00120000","expiration":"2026-12-18","side":"put","strike":120.0,"bid":0.0,"ask":0.0,"mid":null,"last":12.9,"volume":null,"openInterest":0.0,"iv":1.0000000000000003e-05,"delta":-0.645,"gamma":0.0191,"theta":-0.0236,"vega":0.2624,"rho":-0.2511,"greeksSource":"cboe","greeksMissingReason":null},{"symbol":"RBA261218P00125000","expiration":"2026-12-18","side":"put","strike":125.0,"bid":0.0,"ask":0.0,"mid":null,"last":21.2,"volume":2.0,"openInterest":0.0,"iv":1.0000000000000003e-05,"delta":-0.7249,"gamma":0.0175,"theta":-0.0208,"vega":0.2346,"rho":-0.2605,"greeksSource":"cboe","greeksMissingReason":null}]}