{"symbol":"ROG","updated":"2026-07-12T19:37:42.651951-04:00","underlyingPrice":137.52000427246094,"greeks":{"enabled":true,"primarySource":"cboe","fallbackSource":"client-black-scholes","riskFreeRate":null,"dividendYield":null,"total":80,"cboeMatched":80,"computed":0,"missing":0,"cboeContracts":290},"expirations":["2026-07-17","2026-08-21","2026-09-18","2026-11-20","2026-12-18"],"quotes":[{"symbol":"ROG260717C00130000","expiration":"2026-07-17","side":"call","strike":130.0,"bid":6.0,"ask":10.8,"mid":8.4,"last":28.0,"volume":2.0,"openInterest":0.0,"iv":0.9279792358398438,"delta":0.8126,"gamma":0.0291,"theta":-0.1772,"vega":0.0516,"rho":0.0198,"greeksSource":"cboe","greeksMissingReason":null},{"symbol":"ROG260717C00135000","expiration":"2026-07-17","side":"call","strike":135.0,"bid":2.2,"ask":7.0,"mid":4.6,"last":19.75,"volume":null,"openInterest":2.0,"iv":0.8110370458984374,"delta":0.6278,"gamma":0.0407,"theta":-0.2575,"vega":0.0722,"rho":0.0156,"greeksSource":"cboe","greeksMissingReason":null},{"symbol":"ROG260717C00145000","expiration":"2026-07-17","side":"call","strike":145.0,"bid":0.05,"ask":5.0,"mid":2.525,"last":21.36,"volume":1.0,"openInterest":5.0,"iv":0.7575707836914063,"delta":0.243,"gamma":0.0323,"theta":-0.2179,"vega":0.0598,"rho":0.0061,"greeksSource":"cboe","greeksMissingReason":null},{"symbol":"ROG260717C00150000","expiration":"2026-07-17","side":"call","strike":150.0,"bid":0.0,"ask":4.8,"mid":null,"last":4.5,"volume":33.0,"openInterest":0.0,"iv":0.9426275268554687,"delta":0.1273,"gamma":0.0208,"theta":-0.1441,"vega":0.04,"rho":0.0032,"greeksSource":"cboe","greeksMissingReason":null},{"symbol":"ROG260717C00155000","expiration":"2026-07-17","side":"call","strike":155.0,"bid":0.0,"ask":4.8,"mid":null,"last":6.5,"volume":1.0,"openInterest":24.0,"iv":1.125248514404297,"delta":0.0623,"gamma":0.0118,"theta":-0.0834,"vega":0.0236,"rho":0.0016,"greeksSource":"cboe","greeksMissingReason":null},{"symbol":"ROG260717C00160000","expiration":"2026-07-17","side":"call","strike":160.0,"bid":0.0,"ask":4.0,"mid":null,"last":4.5,"volume":1.0,"openInterest":14.0,"iv":1.2094766088867184,"delta":0.0292,"gamma":0.0062,"theta":-0.0444,"vega":0.0129,"rho":0.0007,"greeksSource":"cboe","greeksMissingReason":null},{"symbol":"ROG260717C00165000","expiration":"2026-07-17","side":"call","strike":165.0,"bid":0.0,"ask":1.75,"mid":null,"last":6.5,"volume":1.0,"openInterest":20.0,"iv":1.066899196777344,"delta":0.0135,"gamma":0.0031,"theta":-0.0224,"vega":0.0067,"rho":0.0003,"greeksSource":"cboe","greeksMissingReason":null},{"symbol":"ROG260717C00170000","expiration":"2026-07-17","side":"call","strike":170.0,"bid":0.0,"ask":4.8,"mid":null,"last":5.6,"volume":28.0,"openInterest":27.0,"iv":1.5908223583984373,"delta":0.0062,"gamma":0.0015,"theta":-0.011,"vega":0.0034,"rho":0.0001,"greeksSource":"cboe","greeksMissingReason":null},{"symbol":"ROG260717C00175000","expiration":"2026-07-17","side":"call","strike":175.0,"bid":0.0,"ask":4.8,"mid":null,"last":4.85,"volume":2.0,"openInterest":9.0,"iv":1.7265638671875,"delta":0.0028,"gamma":0.0007,"theta":-0.0053,"vega":0.0017,"rho":0.0001,"greeksSource":"cboe","greeksMissingReason":null},{"symbol":"ROG260717C00180000","expiration":"2026-07-17","side":"call","strike":180.0,"bid":0.0,"ask":4.8,"mid":null,"last":3.0,"volume":null,"openInterest":4.0,"iv":1.85546947265625,"delta":0.0013,"gamma":0.0004,"theta":-0.0026,"vega":0.0008,"rho":0.0,"greeksSource":"cboe","greeksMissingReason":null},{"symbol":"ROG260717C00185000","expiration":"2026-07-17","side":"call","strike":185.0,"bid":0.0,"ask":4.8,"mid":null,"last":3.0,"volume":1.0,"openInterest":2.0,"iv":1.9775391748046878,"delta":0.0006,"gamma":0.0002,"theta":-0.0012,"vega":0.0004,"rho":0.0,"greeksSource":"cboe","greeksMissingReason":null},{"symbol":"ROG260717P00135000","expiration":"2026-07-17","side":"put","strike":135.0,"bid":0.05,"ask":4.9,"mid":2.475,"last":2.52,"volume":1.0,"openInterest":9.0,"iv":0.5161181201171875,"delta":-0.3739,"gamma":0.041,"theta":-0.259,"vega":0.0723,"rho":-0.008,"greeksSource":"cboe","greeksMissingReason":null},{"symbol":"ROG260717P00150000","expiration":"2026-07-17","side":"put","strike":150.0,"bid":10.0,"ask":14.3,"mid":12.15,"last":6.0,"volume":5.0,"openInterest":27.0,"iv":0.8369156933593749,"delta":-0.8773,"gamma":0.021,"theta":-0.1454,"vega":0.0385,"rho":-0.0097,"greeksSource":"cboe","greeksMissingReason":null},{"symbol":"ROG260717P00155000","expiration":"2026-07-17","side":"put","strike":155.0,"bid":15.0,"ask":19.4,"mid":17.2,"last":2.96,"volume":1.0,"openInterest":2.0,"iv":1.031743122558594,"delta":-0.9425,"gamma":0.0118,"theta":-0.0836,"vega":0.022,"rho":-0.0074,"greeksSource":"cboe","greeksMissingReason":null},{"symbol":"ROG260717P00160000","expiration":"2026-07-17","side":"put","strike":160.0,"bid":20.0,"ask":23.4,"mid":21.7,"last":7.1,"volume":null,"openInterest":0.0,"iv":0.948242705078125,"delta":-0.975,"gamma":0.006,"theta":-0.0426,"vega":0.0111,"rho":-0.0045,"greeksSource":"cboe","greeksMissingReason":null},{"symbol":"ROG260821C00135000","expiration":"2026-08-21","side":"call","strike":135.0,"bid":9.0,"ask":13.5,"mid":11.25,"last":32.18,"volume":1.0,"openInterest":1.0,"iv":0.5462691857910158,"delta":0.5925,"gamma":0.0168,"theta":-0.1072,"vega":0.1816,"rho":0.0812,"greeksSource":"cboe","greeksMissingReason":null},{"symbol":"ROG260821C00165000","expiration":"2026-08-21","side":"call","strike":165.0,"bid":0.55,"ask":4.9,"mid":2.725,"last":5.9,"volume":3.0,"openInterest":0.0,"iv":0.5789837023925781,"delta":0.2097,"gamma":0.0108,"theta":-0.0905,"vega":0.1347,"rho":0.0296,"greeksSource":"cboe","greeksMissingReason":null},{"symbol":"ROG260821P00115000","expiration":"2026-08-21","side":"put","strike":115.0,"bid":0.0,"ask":4.8,"mid":null,"last":0.55,"volume":null,"openInterest":1.0,"iv":0.5837443969726561,"delta":-0.1285,"gamma":0.0087,"theta":-0.0601,"vega":0.0982,"rho":-0.0197,"greeksSource":"cboe","greeksMissingReason":null},{"symbol":"ROG260821P00120000","expiration":"2026-08-21","side":"put","strike":120.0,"bid":0.1,"ask":5.0,"mid":2.55,"last":0.85,"volume":null,"openInterest":1.0,"iv":0.5022022436523439,"delta":-0.1812,"gamma":0.0112,"theta":-0.0738,"vega":0.1232,"rho":-0.0276,"greeksSource":"cboe","greeksMissingReason":null},{"symbol":"ROG260821P00125000","expiration":"2026-08-21","side":"put","strike":125.0,"bid":1.0,"ask":5.5,"mid":3.25,"last":1.35,"volume":null,"openInterest":1.0,"iv":0.6058389025878907,"delta":-0.2482,"gamma":0.0137,"theta":-0.0876,"vega":0.1484,"rho":-0.0373,"greeksSource":"cboe","greeksMissingReason":null},{"symbol":"ROG260821P00145000","expiration":"2026-08-21","side":"put","strike":145.0,"bid":11.5,"ask":15.6,"mid":13.55,"last":4.02,"volume":null,"openInterest":1.0,"iv":0.6087685607910158,"delta":-0.578,"gamma":0.0167,"theta":-0.1142,"vega":0.1824,"rho":-0.0792,"greeksSource":"cboe","greeksMissingReason":null},{"symbol":"ROG260821P00150000","expiration":"2026-08-21","side":"put","strike":150.0,"bid":15.0,"ask":18.9,"mid":16.95,"last":5.52,"volume":null,"openInterest":7.0,"iv":0.6053506262207033,"delta":-0.6488,"gamma":0.0156,"theta":-0.1117,"vega":0.1729,"rho":-0.0858,"greeksSource":"cboe","greeksMissingReason":null},{"symbol":"ROG260918C00060000","expiration":"2026-09-18","side":"call","strike":60.0,"bid":75.9,"ask":80.5,"mid":78.2,"last":103.75,"volume":14.0,"openInterest":14.0,"iv":1.0893600219726562,"delta":0.9864,"gamma":0.0006,"theta":-0.0122,"vega":0.019,"rho":0.1099,"greeksSource":"cboe","greeksMissingReason":null},{"symbol":"ROG260918C00080000","expiration":"2026-09-18","side":"call","strike":80.0,"bid":0.0,"ask":0.0,"mid":null,"last":30.0,"volume":null,"openInterest":0.0,"iv":1.0000000000000003e-05,"delta":0.9672,"gamma":0.0016,"theta":-0.0218,"vega":0.0426,"rho":0.1428,"greeksSource":"cboe","greeksMissingReason":null},{"symbol":"ROG260918C00085000","expiration":"2026-09-18","side":"call","strike":85.0,"bid":0.0,"ask":0.0,"mid":null,"last":26.0,"volume":null,"openInterest":0.0,"iv":1.0000000000000003e-05,"delta":0.9586,"gamma":0.002,"theta":-0.0252,"vega":0.0521,"rho":0.1497,"greeksSource":"cboe","greeksMissingReason":null},{"symbol":"ROG260918C00100000","expiration":"2026-09-18","side":"call","strike":100.0,"bid":0.0,"ask":0.0,"mid":null,"last":15.2,"volume":null,"openInterest":0.0,"iv":1.0000000000000003e-05,"delta":0.9146,"gamma":0.0043,"theta":-0.0389,"vega":0.0933,"rho":0.1652,"greeksSource":"cboe","greeksMissingReason":null},{"symbol":"ROG260918C00105000","expiration":"2026-09-18","side":"call","strike":105.0,"bid":0.0,"ask":0.0,"mid":null,"last":13.85,"volume":37.0,"openInterest":0.0,"iv":1.0000000000000003e-05,"delta":0.8906,"gamma":0.0054,"theta":-0.0448,"vega":0.1121,"rho":0.1676,"greeksSource":"cboe","greeksMissingReason":null},{"symbol":"ROG260918C00110000","expiration":"2026-09-18","side":"call","strike":110.0,"bid":0.0,"ask":0.0,"mid":null,"last":11.6,"volume":3.0,"openInterest":0.0,"iv":1.0000000000000003e-05,"delta":0.86,"gamma":0.0067,"theta":-0.0512,"vega":0.1336,"rho":0.1679,"greeksSource":"cboe","greeksMissingReason":null},{"symbol":"ROG260918C00115000","expiration":"2026-09-18","side":"call","strike":115.0,"bid":23.5,"ask":28.3,"mid":25.9,"last":52.0,"volume":2.0,"openInterest":2.0,"iv":0.5148974291992188,"delta":0.8215,"gamma":0.0082,"theta":-0.0581,"vega":0.1569,"rho":0.1657,"greeksSource":"cboe","greeksMissingReason":null},{"symbol":"ROG260918C00125000","expiration":"2026-09-18","side":"call","strike":125.0,"bid":17.0,"ask":21.5,"mid":19.25,"last":37.56,"volume":4.0,"openInterest":5.0,"iv":0.5268602001953125,"delta":0.7186,"gamma":0.0113,"theta":-0.0715,"vega":0.203,"rho":0.1528,"greeksSource":"cboe","greeksMissingReason":null},{"symbol":"ROG260918C00130000","expiration":"2026-09-18","side":"call","strike":130.0,"bid":0.0,"ask":0.0,"mid":null,"last":4.5,"volume":null,"openInterest":0.0,"iv":1.0000000000000003e-05,"delta":0.6559,"gamma":0.0125,"theta":-0.0771,"vega":0.2214,"rho":0.1422,"greeksSource":"cboe","greeksMissingReason":null},{"symbol":"ROG260918C00135000","expiration":"2026-09-18","side":"call","strike":135.0,"bid":11.7,"ask":16.0,"mid":13.85,"last":25.32,"volume":2.0,"openInterest":26.0,"iv":0.532109171142578,"delta":0.5894,"gamma":0.0132,"theta":-0.0811,"vega":0.234,"rho":0.1298,"greeksSource":"cboe","greeksMissingReason":null},{"symbol":"ROG260918C00140000","expiration":"2026-09-18","side":"call","strike":140.0,"bid":9.6,"ask":14.0,"mid":11.8,"last":25.99,"volume":20.0,"openInterest":20.0,"iv":0.5414474566650394,"delta":0.5226,"gamma":0.0135,"theta":-0.0834,"vega":0.2397,"rho":0.1165,"greeksSource":"cboe","greeksMissingReason":null},{"symbol":"ROG260918C00145000","expiration":"2026-09-18","side":"call","strike":145.0,"bid":7.9,"ask":12.0,"mid":9.95,"last":22.24,"volume":1.0,"openInterest":13.0,"iv":0.5465133239746094,"delta":0.4588,"gamma":0.0133,"theta":-0.084,"vega":0.2388,"rho":0.1032,"greeksSource":"cboe","greeksMissingReason":null},{"symbol":"ROG260918C00150000","expiration":"2026-09-18","side":"call","strike":150.0,"bid":0.0,"ask":0.0,"mid":null,"last":10.0,"volume":20.0,"openInterest":0.0,"iv":0.062509375,"delta":0.4004,"gamma":0.0128,"theta":-0.083,"vega":0.2327,"rho":0.0907,"greeksSource":"cboe","greeksMissingReason":null},{"symbol":"ROG260918C00155000","expiration":"2026-09-18","side":"call","strike":155.0,"bid":4.6,"ask":9.0,"mid":6.8,"last":18.02,"volume":14.0,"openInterest":57.0,"iv":0.5465133239746094,"delta":0.3485,"gamma":0.012,"theta":-0.0809,"vega":0.2228,"rho":0.0794,"greeksSource":"cboe","greeksMissingReason":null},{"symbol":"ROG260918C00160000","expiration":"2026-09-18","side":"call","strike":160.0,"bid":3.3,"ask":8.0,"mid":5.65,"last":15.96,"volume":1.0,"openInterest":1.0,"iv":0.5501753967285157,"delta":0.3033,"gamma":0.0111,"theta":-0.078,"vega":0.2106,"rho":0.0693,"greeksSource":"cboe","greeksMissingReason":null},{"symbol":"ROG260918C00165000","expiration":"2026-09-18","side":"call","strike":165.0,"bid":4.0,"ask":7.0,"mid":5.5,"last":5.0,"volume":1.0,"openInterest":36.0,"iv":0.5948526843261719,"delta":0.2643,"gamma":0.0102,"theta":-0.0745,"vega":0.1972,"rho":0.0605,"greeksSource":"cboe","greeksMissingReason":null},{"symbol":"ROG260918C00170000","expiration":"2026-09-18","side":"call","strike":170.0,"bid":1.15,"ask":6.0,"mid":3.575,"last":12.47,"volume":1.0,"openInterest":1.0,"iv":0.540287800292969,"delta":0.2309,"gamma":0.0092,"theta":-0.0708,"vega":0.1836,"rho":0.053,"greeksSource":"cboe","greeksMissingReason":null},{"symbol":"ROG260918C00210000","expiration":"2026-09-18","side":"call","strike":210.0,"bid":0.0,"ask":4.8,"mid":null,"last":5.7,"volume":1.0,"openInterest":1.0,"iv":0.7412135253906249,"delta":0.0895,"gamma":0.0042,"theta":-0.0435,"vega":0.0976,"rho":0.0205,"greeksSource":"cboe","greeksMissingReason":null},{"symbol":"ROG260918P00065000","expiration":"2026-09-18","side":"put","strike":65.0,"bid":0.0,"ask":0.0,"mid":null,"last":1.0,"volume":null,"openInterest":0.0,"iv":0.2500075,"delta":-0.0153,"gamma":0.0007,"theta":-0.0141,"vega":0.0233,"rho":-0.0043,"greeksSource":"cboe","greeksMissingReason":null},{"symbol":"ROG260918P00080000","expiration":"2026-09-18","side":"put","strike":80.0,"bid":0.0,"ask":0.0,"mid":null,"last":2.5,"volume":null,"openInterest":0.0,"iv":0.2500075,"delta":-0.0314,"gamma":0.0016,"theta":-0.0219,"vega":0.0427,"rho":-0.0088,"greeksSource":"cboe","greeksMissingReason":null},{"symbol":"ROG260918P00090000","expiration":"2026-09-18","side":"put","strike":90.0,"bid":0.0,"ask":0.0,"mid":null,"last":4.5,"volume":32.0,"openInterest":0.0,"iv":0.2500075,"delta":-0.0512,"gamma":0.0026,"theta":-0.0293,"vega":0.0636,"rho":-0.0141,"greeksSource":"cboe","greeksMissingReason":null},{"symbol":"ROG260918P00110000","expiration":"2026-09-18","side":"put","strike":110.0,"bid":0.0,"ask":4.8,"mid":null,"last":0.7,"volume":1.0,"openInterest":2.0,"iv":0.5229539892578124,"delta":-0.1394,"gamma":0.0068,"theta":-0.0516,"vega":0.1341,"rho":-0.0375,"greeksSource":"cboe","greeksMissingReason":null},{"symbol":"ROG260918P00120000","expiration":"2026-09-18","side":"put","strike":120.0,"bid":1.05,"ask":5.9,"mid":3.475,"last":1.5,"volume":1.0,"openInterest":1.0,"iv":0.5754436987304687,"delta":-0.2257,"gamma":0.0099,"theta":-0.0656,"vega":0.1814,"rho":-0.0596,"greeksSource":"cboe","greeksMissingReason":null},{"symbol":"ROG260918P00125000","expiration":"2026-09-18","side":"put","strike":125.0,"bid":2.55,"ask":7.4,"mid":4.975,"last":2.2,"volume":null,"openInterest":1.0,"iv":0.5592085095214845,"delta":-0.282,"gamma":0.0114,"theta":-0.0723,"vega":0.2036,"rho":-0.0736,"greeksSource":"cboe","greeksMissingReason":null},{"symbol":"ROG260918P00135000","expiration":"2026-09-18","side":"put","strike":135.0,"bid":7.5,"ask":11.8,"mid":9.65,"last":4.2,"volume":1.0,"openInterest":0.0,"iv":0.5523116058349609,"delta":-0.4128,"gamma":0.0134,"theta":-0.0823,"vega":0.2342,"rho":-0.1048,"greeksSource":"cboe","greeksMissingReason":null},{"symbol":"ROG260918P00140000","expiration":"2026-09-18","side":"put","strike":140.0,"bid":10.6,"ask":15.3,"mid":12.95,"last":11.11,"volume":null,"openInterest":1.0,"iv":0.5843547424316407,"delta":-0.4806,"gamma":0.0137,"theta":-0.0849,"vega":0.2394,"rho":-0.1197,"greeksSource":"cboe","greeksMissingReason":null},{"symbol":"ROG260918P00150000","expiration":"2026-09-18","side":"put","strike":150.0,"bid":16.5,"ask":21.3,"mid":18.9,"last":10.4,"volume":1.0,"openInterest":2.0,"iv":0.5711712805175782,"delta":-0.6051,"gamma":0.0131,"theta":-0.085,"vega":0.2312,"rho":-0.1452,"greeksSource":"cboe","greeksMissingReason":null},{"symbol":"ROG260918P00160000","expiration":"2026-09-18","side":"put","strike":160.0,"bid":24.0,"ask":28.6,"mid":26.3,"last":30.0,"volume":null,"openInterest":2.0,"iv":0.5726361096191408,"delta":-0.7047,"gamma":0.0114,"theta":-0.0805,"vega":0.2065,"rho":-0.1576,"greeksSource":"cboe","greeksMissingReason":null},{"symbol":"ROG261120C00165000","expiration":"2026-11-20","side":"call","strike":165.0,"bid":7.0,"ask":11.5,"mid":9.25,"last":18.6,"volume":4.0,"openInterest":8.0,"iv":0.5570723004150393,"delta":0.3558,"gamma":0.0086,"theta":-0.0602,"vega":0.3096,"rho":0.1466,"greeksSource":"cboe","greeksMissingReason":null},{"symbol":"ROG261120C00170000","expiration":"2026-11-20","side":"call","strike":170.0,"bid":6.0,"ask":10.5,"mid":8.25,"last":22.25,"volume":null,"openInterest":1.0,"iv":0.5612836840820312,"delta":0.3231,"gamma":0.0082,"theta":-0.0584,"vega":0.2983,"rho":0.1338,"greeksSource":"cboe","greeksMissingReason":null},{"symbol":"ROG261120P00105000","expiration":"2026-11-20","side":"put","strike":105.0,"bid":0.5,"ask":5.0,"mid":2.75,"last":1.7,"volume":1.0,"openInterest":1.0,"iv":0.5690350714111327,"delta":-0.1374,"gamma":0.0053,"theta":-0.0342,"vega":0.1832,"rho":-0.0726,"greeksSource":"cboe","greeksMissingReason":null},{"symbol":"ROG261218C00070000","expiration":"2026-12-18","side":"call","strike":70.0,"bid":67.7,"ask":71.5,"mid":69.6,"last":73.5,"volume":5.0,"openInterest":4.0,"iv":0.7666038964843751,"delta":0.9781,"gamma":0.001,"theta":-0.0048,"vega":0.0471,"rho":0.2896,"greeksSource":"cboe","greeksMissingReason":null},{"symbol":"ROG261218C00085000","expiration":"2026-12-18","side":"call","strike":85.0,"bid":72.0,"ask":76.5,"mid":74.25,"last":59.5,"volume":null,"openInterest":20.0,"iv":1.5567649114990232,"delta":0.9449,"gamma":0.0023,"theta":-0.0138,"vega":0.1019,"rho":0.3311,"greeksSource":"cboe","greeksMissingReason":null},{"symbol":"ROG261218C00100000","expiration":"2026-12-18","side":"call","strike":100.0,"bid":39.7,"ask":44.5,"mid":42.1,"last":68.2,"volume":null,"openInterest":1.0,"iv":0.5563398858642579,"delta":0.8795,"gamma":0.0043,"theta":-0.0265,"vega":0.1837,"rho":0.3482,"greeksSource":"cboe","greeksMissingReason":null},{"symbol":"ROG261218C00110000","expiration":"2026-12-18","side":"call","strike":110.0,"bid":36.5,"ask":40.9,"mid":38.7,"last":27.28,"volume":null,"openInterest":2.0,"iv":0.6905548522949221,"delta":0.8154,"gamma":0.0058,"theta":-0.0358,"vega":0.2439,"rho":0.3427,"greeksSource":"cboe","greeksMissingReason":null},{"symbol":"ROG261218C00115000","expiration":"2026-12-18","side":"call","strike":115.0,"bid":33.0,"ask":37.8,"mid":35.4,"last":25.47,"volume":null,"openInterest":6.0,"iv":0.6777986322021485,"delta":0.778,"gamma":0.0066,"theta":-0.0402,"vega":0.2722,"rho":0.3352,"greeksSource":"cboe","greeksMissingReason":null},{"symbol":"ROG261218C00120000","expiration":"2026-12-18","side":"call","strike":120.0,"bid":30.0,"ask":34.4,"mid":32.2,"last":16.9,"volume":1.0,"openInterest":1.0,"iv":0.6635775830078127,"delta":0.738,"gamma":0.0072,"theta":-0.0443,"vega":0.2978,"rho":0.3246,"greeksSource":"cboe","greeksMissingReason":null},{"symbol":"ROG261218C00130000","expiration":"2026-12-18","side":"call","strike":130.0,"bid":24.0,"ask":28.5,"mid":26.25,"last":23.04,"volume":2.0,"openInterest":3.0,"iv":0.6356237609863282,"delta":0.6535,"gamma":0.0081,"theta":-0.0508,"vega":0.3372,"rho":0.2977,"greeksSource":"cboe","greeksMissingReason":null},{"symbol":"ROG261218C00135000","expiration":"2026-12-18","side":"call","strike":135.0,"bid":18.2,"ask":23.0,"mid":20.6,"last":39.18,"volume":1.0,"openInterest":2.0,"iv":0.5394333166503908,"delta":0.6106,"gamma":0.0084,"theta":-0.0532,"vega":0.3504,"rho":0.2819,"greeksSource":"cboe","greeksMissingReason":null},{"symbol":"ROG261218C00140000","expiration":"2026-12-18","side":"call","strike":140.0,"bid":16.4,"ask":21.0,"mid":18.7,"last":38.15,"volume":1.0,"openInterest":6.0,"iv":0.5462691857910158,"delta":0.5683,"gamma":0.0086,"theta":-0.0549,"vega":0.3591,"rho":0.2657,"greeksSource":"cboe","greeksMissingReason":null},{"symbol":"ROG261218C00145000","expiration":"2026-12-18","side":"call","strike":145.0,"bid":14.7,"ask":19.0,"mid":16.85,"last":27.5,"volume":8.0,"openInterest":12.0,"iv":0.549076774902344,"delta":0.5272,"gamma":0.0086,"theta":-0.056,"vega":0.3636,"rho":0.2491,"greeksSource":"cboe","greeksMissingReason":null},{"symbol":"ROG261218C00150000","expiration":"2026-12-18","side":"call","strike":150.0,"bid":12.7,"ask":17.5,"mid":15.1,"last":27.49,"volume":5.0,"openInterest":53.0,"iv":0.5496260858154298,"delta":0.4877,"gamma":0.0086,"theta":-0.0565,"vega":0.3643,"rho":0.2325,"greeksSource":"cboe","greeksMissingReason":null},{"symbol":"ROG261218C00160000","expiration":"2026-12-18","side":"call","strike":160.0,"bid":9.7,"ask":14.5,"mid":12.1,"last":13.4,"volume":1.0,"openInterest":1.0,"iv":0.5510909149169922,"delta":0.4146,"gamma":0.0083,"theta":-0.056,"vega":0.356,"rho":0.2005,"greeksSource":"cboe","greeksMissingReason":null},{"symbol":"ROG261218C00165000","expiration":"2026-12-18","side":"call","strike":165.0,"bid":8.3,"ask":13.0,"mid":10.65,"last":25.0,"volume":2.0,"openInterest":58.0,"iv":0.5469405657958986,"delta":0.3815,"gamma":0.0081,"theta":-0.0551,"vega":0.3484,"rho":0.1858,"greeksSource":"cboe","greeksMissingReason":null},{"symbol":"ROG261218C00170000","expiration":"2026-12-18","side":"call","strike":170.0,"bid":7.6,"ask":12.0,"mid":9.8,"last":19.87,"volume":1.0,"openInterest":11.0,"iv":0.5565229895019532,"delta":0.3508,"gamma":0.0078,"theta":-0.054,"vega":0.3387,"rho":0.1716,"greeksSource":"cboe","greeksMissingReason":null},{"symbol":"ROG261218C00175000","expiration":"2026-12-18","side":"call","strike":175.0,"bid":7.0,"ask":11.3,"mid":9.15,"last":2.0,"volume":5.0,"openInterest":5.0,"iv":0.5690961059570312,"delta":0.3223,"gamma":0.0075,"theta":-0.0526,"vega":0.3279,"rho":0.1585,"greeksSource":"cboe","greeksMissingReason":null},{"symbol":"ROG261218C00180000","expiration":"2026-12-18","side":"call","strike":180.0,"bid":5.5,"ask":10.0,"mid":7.75,"last":21.1,"volume":2.0,"openInterest":11.0,"iv":0.5553022985839844,"delta":0.296,"gamma":0.0072,"theta":-0.051,"vega":0.316,"rho":0.1462,"greeksSource":"cboe","greeksMissingReason":null},{"symbol":"ROG261218C00195000","expiration":"2026-12-18","side":"call","strike":195.0,"bid":3.1,"ask":7.5,"mid":5.3,"last":12.25,"volume":1.0,"openInterest":2.0,"iv":0.5495040167236329,"delta":0.2295,"gamma":0.0062,"theta":-0.0456,"vega":0.2774,"rho":0.1144,"greeksSource":"cboe","greeksMissingReason":null},{"symbol":"ROG261218C00200000","expiration":"2026-12-18","side":"call","strike":200.0,"bid":3.0,"ask":7.0,"mid":5.0,"last":4.2,"volume":1.0,"openInterest":2.0,"iv":0.5611616149902343,"delta":0.2109,"gamma":0.0058,"theta":-0.0437,"vega":0.2644,"rho":0.1054,"greeksSource":"cboe","greeksMissingReason":null},{"symbol":"ROG261218C00210000","expiration":"2026-12-18","side":"call","strike":210.0,"bid":1.8,"ask":6.0,"mid":3.9,"last":11.25,"volume":1.0,"openInterest":419.0,"iv":0.5585371295166017,"delta":0.1785,"gamma":0.0052,"theta":-0.04,"vega":0.2389,"rho":0.0896,"greeksSource":"cboe","greeksMissingReason":null},{"symbol":"ROG261218P00095000","expiration":"2026-12-18","side":"put","strike":95.0,"bid":0.0,"ask":4.8,"mid":null,"last":1.1,"volume":2.0,"openInterest":4.0,"iv":0.6280554772949221,"delta":-0.095,"gamma":0.0036,"theta":-0.0243,"vega":0.1554,"rho":-0.0619,"greeksSource":"cboe","greeksMissingReason":null},{"symbol":"ROG261218P00100000","expiration":"2026-12-18","side":"put","strike":100.0,"bid":0.1,"ask":5.0,"mid":2.55,"last":1.5,"volume":2.0,"openInterest":2.0,"iv":0.5763592169189453,"delta":-0.1214,"gamma":0.0044,"theta":-0.0287,"vega":0.1849,"rho":-0.0788,"greeksSource":"cboe","greeksMissingReason":null},{"symbol":"ROG261218P00105000","expiration":"2026-12-18","side":"put","strike":105.0,"bid":1.05,"ask":5.9,"mid":3.475,"last":2.0,"volume":2.0,"openInterest":2.0,"iv":0.5553022985839844,"delta":-0.1521,"gamma":0.0052,"theta":-0.0333,"vega":0.2157,"rho":-0.0985,"greeksSource":"cboe","greeksMissingReason":null},{"symbol":"ROG261218P00110000","expiration":"2026-12-18","side":"put","strike":110.0,"bid":2.15,"ask":7.0,"mid":4.575,"last":6.1,"volume":3.0,"openInterest":29.0,"iv":0.5376022802734376,"delta":-0.1867,"gamma":0.006,"theta":-0.0379,"vega":0.2461,"rho":-0.1203,"greeksSource":"cboe","greeksMissingReason":null},{"symbol":"ROG261218P00120000","expiration":"2026-12-18","side":"put","strike":120.0,"bid":5.5,"ask":10.3,"mid":7.9,"last":4.0,"volume":10.0,"openInterest":10.0,"iv":0.5238695074462891,"delta":-0.2658,"gamma":0.0074,"theta":-0.0463,"vega":0.2995,"rho":-0.1691,"greeksSource":"cboe","greeksMissingReason":null},{"symbol":"ROG261218P00145000","expiration":"2026-12-18","side":"put","strike":145.0,"bid":18.0,"ask":22.7,"mid":20.35,"last":22.1,"volume":null,"openInterest":0.0,"iv":0.5043384527587891,"delta":-0.483,"gamma":0.009,"theta":-0.0581,"vega":0.3622,"rho":-0.2899,"greeksSource":"cboe","greeksMissingReason":null},{"symbol":"ROG261218P00150000","expiration":"2026-12-18","side":"put","strike":150.0,"bid":0.0,"ask":0.0,"mid":null,"last":19.7,"volume":null,"openInterest":0.0,"iv":1.0000000000000003e-05,"delta":-0.5241,"gamma":0.009,"theta":-0.0586,"vega":0.3616,"rho":-0.3119,"greeksSource":"cboe","greeksMissingReason":null},{"symbol":"ROG261218P00190000","expiration":"2026-12-18","side":"put","strike":190.0,"bid":50.5,"ask":55.0,"mid":52.75,"last":49.45,"volume":null,"openInterest":10.0,"iv":0.4116269775390625,"delta":-0.7779,"gamma":0.0072,"theta":-0.0505,"vega":0.2654,"rho":-0.3637,"greeksSource":"cboe","greeksMissingReason":null}]}